<?xml version="1.0" encoding="UTF-8"?>
<listofFileNames>
  <header>
    <authorName>Albertus Magnus</authorName>
    <commentaryName>De Anima</commentaryName>
    <commentaryid>albertusdeanima</commentaryid>
    <commentaryslug>admda</commentaryslug>
    <authorUri>http://scta.info/resource/Albert</authorUri>
    <parentUri>http://scta.info/resource/albertusdeanima</parentUri>
    <parentWorkGroup>http://scta.info/resource/deanima</parentWorkGroup>
    <textfilesdir>/Users/jcwitt/Projects/scta/scta-texts/albertusdeanima/</textfilesdir>
    <webbase>null</webbase>
    <questionListSource/>
    <questionListOriginalEditor>Bruno Tremblay</questionListOriginalEditor>
    <questionListEncoder>Jeffrey C. Witt</questionListEncoder>
    <gitRepoBase type="toplevel">https://github.com/scta-texts/</gitRepoBase>
    <sponsors>
      <sponsor id="albertusMagnusEcorpus">
        <name>Alberti Magni e-corpus</name>
        <logo>http://albertusmagnus.uwaterloo.ca/Images/Index_CLM27029.png</logo>
        <link>http://albertusmagnus.uwaterloo.ca/</link>
      </sponsor>
    </sponsors>
    <hasWitnesses>
      <witness id="B5">
        <slug>Borgnet1890v5</slug>
        <title>Borgnet, 1890, Volume 5</title>
        <initial>B5</initial>
      </witness>
    </hasWitnesses>
  </header>
  <div id="body">
    <div id="admda-l1" type="da-liber1">
      <head>Liber I</head>
      <div id="admda-l1t1">
        <head>Liber I, Tractatus I</head>
        <questionTitlte>DE MODO QUO COGNOSCENDA EST ANIMA.</questionTitlte>
        <item id="admda-l1t1c1">
          <fileName filestem="admda-l1t1c1"/>
          <title> CAPUT I.</title>
          <questionTitle>Et est digressio declarans, quod scientia naturalis est de anima, et quis
            ejus ordo.</questionTitle>
          <hasWitnesses>
            <witness ref="#B5">
              <folio>117</folio>
              <folio>118</folio>
              <folio>119</folio>
            </witness>
          </hasWitnesses>
        </item>
        <item id="admda-l1t1c2">
          <fileName filestem="admda-l1t1c2"/>
          <title> CAPUT II.</title>
          <questionTitle>De nobilitate et utilitate scientiae de anima.</questionTitle>
          <hasWitnesses>
            <witness ref="#B5">
              <folio>119</folio>
              <folio>120</folio>
            </witness>
          </hasWitnesses>
        </item>
        <item id="admda-l1t1c3">
          <fileName filestem="admda-l1t1c3"/>
          <title>CAPUT III.</title>
          <questionTitle>De quaesitis quid sit subjectum hujus scientiae, et de difficultate
            ipsius.</questionTitle>
          <hasWitnesses>
            <witness ref="#B5">
              <folio>120</folio>
              <folio>121</folio>
              <folio>122</folio>
            </witness>
          </hasWitnesses>
        </item>
        <item id="admda-l1t1c4">
          <fileName filestem="admda-l1t1c4"/>
          <title>CAPUT IV.</title>
          <questionTitle>Quae oportet inquirere ad investigandum propriam animae
            diffinitionem.</questionTitle>
          <hasWitnesses>
            <witness ref="#B5">
              <folio>122</folio>
              <folio>123</folio>
              <folio>124</folio>
            </witness>
          </hasWitnesses>
        </item>
        <item id="admda-l1t1c5">
          <fileName filestem="admda-l1t1c5"/>
          <title>CAPUT V</title>
          <questionTitle>Quo ordine oportet procedere quaerentem de his quae spectant ad scientiam
            de anima.</questionTitle>
          <hasWitnesses>
            <witness ref="#B5">
              <folio>125</folio>
              <folio>126</folio>
              <folio>127</folio>
            </witness>
          </hasWitnesses>
        </item>
        <item id="admda-l1t1c6">
          <fileName filestem="admda-l1t1c6"/>
          <title>CAPUT VI.</title>
          <questionTitle>Quod oportet tractantem de anima inquirere utrum habeat aliquas operationes
            proprias, aut non.</questionTitle>
          <hasWitnesses>
            <witness ref="#B5">
              <folio>127</folio>
              <folio>128</folio>
              <folio>129</folio>
              <folio>130</folio>
            </witness>
          </hasWitnesses>
        </item>
        <item id="admda-l1t1c7">
          <fileName filestem="admda-l1t1c7"/>
          <title>CAPUT VII.</title>
          <questionTitle>Qualiter differenter considerat physicus de eis quae hic quaeruntur, a
            dialectico et mathematico et metaphysico et mechanico, in quo est digressio
            quaedam.</questionTitle>
          <hasWitnesses>
            <witness ref="#B5">
              <folio>130</folio>
              <folio>131</folio>
              <folio>132</folio>
              <folio>133</folio>
              <folio>134</folio>
            </witness>
          </hasWitnesses>
        </item>
      </div>
      <div id="admda-l1t2">
        <head>Liber I, Tractatus II</head>
        <questionTitlte>DE ANIMA SECUNDUM OPINIONES ALIORUM.</questionTitlte>
        <item id="admda-l1t2c1">
          <fileName filestem="admda-l1t2c1"/>
          <title>CAPUT I.</title>
          <questionTitle>De his qui diffiniebant animam per hoc quod ipsa est motivum
            quoddam.</questionTitle>
          <hasWitnesses>
            <witness ref="#B5">
              <folio>135</folio>
              <folio>136</folio>
              <folio>137</folio>
              <folio>138</folio>
            </witness>
          </hasWitnesses>
        </item>
        <item id="admda-l1t2c2">
          <fileName filestem="admda-l1t2c2"/>
          <title>CAPUT II.</title>
          <questionTitle>De opinionibus eorum qui animam per cognoscitivum diffiniendam esse
            dixerunt.</questionTitle>
          <hasWitnesses>
            <witness ref="#B5">
              <folio>139</folio>
              <folio>140</folio>
              <folio>141</folio>
              <folio>142</folio>
            </witness>
          </hasWitnesses>
        </item>
        <item id="admda-l1t2c3">
          <fileName filestem="admda-l1t2c3"/>
          <title>CAPUT III.</title>
          <questionTitle>De opinione quae et motivo et cognoscitivo animam dicit diffiniendam : in
            quo etiam est de opinionum collatione.</questionTitle>
          <hasWitnesses>
            <witness ref="#B5">
              <folio>142</folio>
              <folio>143</folio>
              <folio>144</folio>
            </witness>
          </hasWitnesses>
        </item>
        <item id="admda-l1t2c4">
          <fileName filestem="admda-l1t2c4"/>
          <title>CAPUT IV.</title>
          <questionTitle>De tribus in summa, per quae anima ab Antiquis diffiniebatur, quae sunt
            motivum, cognoscitivum et incorporeum.</questionTitle>
          <hasWitnesses>
            <witness ref="#B5">
              <folio>145</folio>
              <folio>146</folio>
              <folio>147</folio>
            </witness>
          </hasWitnesses>
        </item>
        <item id="admda-l1t2c5">
          <fileName filestem="admda-l1t2c5"/>
          <title>CAPUT V.</title>
          <questionTitle>De contradictione opinionum in communi, quae diffiniebant animam per
            motivum suiipsius.</questionTitle>
          <hasWitnesses>
            <witness ref="#B5">
              <folio>147</folio>
              <folio>148</folio>
              <folio>149</folio>
              <folio>150</folio>
            </witness>
          </hasWitnesses>
        </item>
        <item id="admda-l1t2c6">
          <fileName filestem="admda-l1t2c6"/>
          <title>CAPUT VI.</title>
          <questionTitle/>
          <hasWitnesses>
            <witness ref="#B5">
              <folio>151</folio>
              <folio>152</folio>
              <folio>153</folio>
            </witness>
          </hasWitnesses>
        </item>
        <item id="admda-l1t2c7">
          <fileName filestem="admda-l1t2c7"/>
          <title>CAPUT VII.</title>
          <questionTitle>De disputatione contra opiniones Democriti et Platonis de motibus animae,
            quibus movetur in corpore et movet corpus.</questionTitle>
          <hasWitnesses>
            <witness ref="#B5">
              <folio>153</folio>
              <folio>154</folio>
              <folio>155</folio>
              <folio>156</folio>
              <folio>157</folio>
              <folio>158</folio>
              <folio>159</folio>
              <folio>160</folio>
            </witness>
          </hasWitnesses>
        </item>
        <item id="admda-l1t2c8">
          <fileName filestem="admda-l1t2c8"/>
          <title>CAPUT VIII.</title>
          <questionTitle>De improbatione opinionis quae dixit animam esse harmoniam corporis
            commixti.</questionTitle>
          <hasWitnesses>
            <witness ref="#B5">
              <folio>160</folio>
              <folio>161</folio>
              <folio>162</folio>
              <folio>163</folio>
            </witness>
          </hasWitnesses>
        </item>
        <item id="admda-l1t2c9">
          <fileName filestem="admda-l1t2c9"/>
          <title>CAPUT IX.</title>
          <questionTitle>De solutione objectionis qua videtur ex alterantibus probari, quod anima
            movetur per se physice : et in illo est bona demonstratio de intellectualis animae
            immortalitate.</questionTitle>
          <hasWitnesses>
            <witness ref="#B5">
              <folio>163</folio>
              <folio>164</folio>
              <folio>165</folio>
              <folio>166</folio>
            </witness>
          </hasWitnesses>
        </item>
        <item id="admda-l1t2c10">
          <fileName filestem="admda-l1t2c10"/>
          <title>CAPUT X.</title>
          <questionTitle>De improbatione opinionis quae dicit animam esse numerum seipsum
            moventem.</questionTitle>
          <hasWitnesses>
            <witness ref="#B5">
              <folio>166</folio>
              <folio>167</folio>
              <folio>168</folio>
              <folio>169</folio>
              <folio>170</folio>
            </witness>
          </hasWitnesses>
        </item>
        <item id="admda-l1t2c11">
          <fileName filestem="admda-l1t2c11"/>
          <title>CAPUT XI.</title>
          <questionTitle>De improbatione operationis eorum qui diffinierunt animam per
            cognoscitivum, dicentium simile simili cognosci, et ideo animam esse principium
            omnium.</questionTitle>
          <hasWitnesses>
            <witness ref="#B5">
              <folio>170</folio>
              <folio>171</folio>
              <folio>172</folio>
            </witness>
          </hasWitnesses>
        </item>
        <item id="admda-l1t2c12">
          <fileName filestem="admda-l1t2c12"/>
          <title>CAPUT XII.</title>
          <questionTitle>Utrum cognoscatur simile simili, sicut dixit Empedocles.</questionTitle>
          <hasWitnesses>
            <witness ref="#B5">
              <folio>172</folio>
              <folio>173</folio>
              <folio>174</folio>
              <folio>175</folio>
              <folio>176</folio>
            </witness>
          </hasWitnesses>
        </item>
        <item id="admda-l1t2c13">
          <fileName filestem="admda-l1t2c13"/>
          <title>CAPUT XIII.</title>
          <questionTitle>De causa illius opinionis, quae dixit animam esse ex elementis, et
            specialiter ex aere : et est digressio in eo declarans diversas causas, et tres
            opiniones circa hoc.</questionTitle>
          <hasWitnesses>
            <witness ref="#B5">
              <folio>176</folio>
              <folio>177</folio>
              <folio>178</folio>
              <folio>179</folio>
              <folio>180</folio>
            </witness>
          </hasWitnesses>
        </item>
        <item id="admda-l1t2c14">
          <fileName filestem="admda-l1t2c14"/>
          <title>CAPUT XIV.</title>
          <questionTitle>Et est digressio declarans causam dicti Antiquorum, quo dixerunt simile
            simili cognosci.</questionTitle>
          <hasWitnesses>
            <witness ref="#B5">
              <folio>180</folio>
              <folio>181</folio>
              <folio>182</folio>
            </witness>
          </hasWitnesses>
        </item>
        <item id="admda-l1t2c15">
          <fileName filestem="admda-l1t2c15"/>
          <title>CAPUT XV.</title>
          <questionTitle>Utrum anima diversa agat per unam substantiam et diversas potentias, vel
            per plures substantias et plures potentias : in quo etiam habetur utrum vegetabilis et
            sensibilis et rationalis una sit substantia in homine.</questionTitle>
          <hasWitnesses>
            <witness ref="#B5">
              <folio>182</folio>
              <folio>183</folio>
              <folio>184</folio>
              <folio>185</folio>
              <folio>186</folio>
              <folio>187</folio>
              <folio>188</folio>
            </witness>
          </hasWitnesses>
        </item>
        <item id="admda-l1t2c16">
          <fileName filestem="admda-l1t2c16"/>
          <title>CAPUT XVI.</title>
          <questionTitle>De dubitatione quae movetur de eo quod unit potentias animae, utrum ratio
            communis vel substantia realis, cujus vires animae sunt partes.</questionTitle>
          <hasWitnesses>
            <witness ref="#B5">
              <folio>188</folio>
              <folio>189</folio>
              <folio>190</folio>
            </witness>
          </hasWitnesses>
        </item>
      </div>
    </div>
    <div id="admda-l2" type="da-liber2">
      <head>Liber II</head>
      <questionTitle>DE ANIMA SECUNDUM SUBSTANTIAM ET PARTES EJUS, QUAE SUNT VEGETABILIS, SENSIBILIS
        ET RATIONALIS.</questionTitle>
      <div id="admda-l2t1">
        <head>Liber II, Tractatus I</head>
        <questionTitle>DE SUBSTANTIA ANIMAE SECUNDUM SE.</questionTitle>
        <item id="admda-l2t1c1">
          <fileName filestem="admda-l2t1c1"/>
          <title>CAPUT I.</title>
          <questionTitle>Quae sit libri intentio, et qualiter diffinitionem animae venari
            contingit.</questionTitle>
          <hasWitnesses>
            <witness ref="#B5">
              <folio>191</folio>
              <folio>192</folio>
              <folio>193</folio>
            </witness>
          </hasWitnesses>
        </item>
        <item id="admda-l2t1c2">
          <fileName filestem="admda-l2t1c2"/>
          <title>CAPUT II.</title>
          <questionTitle>De universali animae diffinitione, quae dicit quid est anima
            universaliter.</questionTitle>
          <hasWitnesses>
            <witness ref="#B5">
              <folio>194</folio>
              <folio>195</folio>
            </witness>
          </hasWitnesses>
        </item>
        <item id="admda-l2t1c3">
          <fileName filestem="admda-l2t1c3"/>
          <title>CAPUT III.</title>
          <questionTitle>De datae diffinitionis explanatione, et est digressio
            quaedam.</questionTitle>
          <hasWitnesses>
            <witness ref="#B5">
              <folio>195</folio>
              <folio>196</folio>
              <folio>197</folio>
              <folio>198</folio>
            </witness>
          </hasWitnesses>
        </item>
        <item id="admda-l2t1c4">
          <fileName filestem="admda-l2t1c4"/>
          <title>CAPUT IV.</title>
          <questionTitle>In quo ex praedictis demonstratur quae anima separabilis est, et quae
            non.</questionTitle>
          <hasWitnesses>
            <witness ref="#B5">
              <folio>198</folio>
              <folio>199</folio>
            </witness>
          </hasWitnesses>
        </item>
        <item id="admda-l2t1c5">
          <fileName filestem="admda-l2t1c5"/>
          <title>CAPUT V.</title>
          <questionTitle>In quo probatur, quod oportet quaerere aliam adhuc diffinitionem, quae
            dicit causam superius habitae.</questionTitle>
          <hasWitnesses>
            <witness ref="#B5">
              <folio>199</folio>
              <folio>200</folio>
              <folio>201</folio>
            </witness>
          </hasWitnesses>
        </item>
        <item id="admda-l2t1c6">
          <fileName filestem="admda-l2t1c6"/>
          <title>CAPUT VI.</title>
          <questionTitle>De diffinitione animae dicente propter quid.</questionTitle>
          <hasWitnesses>
            <witness ref="#B5">
              <folio>201</folio>
              <folio>202</folio>
              <folio>203</folio>
            </witness>
          </hasWitnesses>
        </item>
        <item id="admda-l2t1c7">
          <fileName filestem="admda-l2t1c7"/>
          <title>CAPUT VII.</title>
          <questionTitle>Utrum quaelibet virium animae sit anima, et utrum sit tota in
            toto.</questionTitle>
          <hasWitnesses>
            <witness ref="#B5">
              <folio>203</folio>
              <folio>204</folio>
              <folio>205</folio>
            </witness>
          </hasWitnesses>
        </item>
        <item id="admda-l2t1c8">
          <fileName filestem="admda-l2t1c8"/>
          <title>CAPUT VIII.</title>
          <questionTitle>Qualiter intellectus est alterum genus animae et separabilis : et qualiter
            est umbra intelligentiae, et sensibilis est umbra intellectus, etiam vegetabilis est
            umbra sensibilis.</questionTitle>
          <hasWitnesses>
            <witness ref="#B5">
              <folio>205</folio>
              <folio>206</folio>
            </witness>
          </hasWitnesses>
        </item>
        <item id="admda-l2t1c9">
          <fileName filestem="admda-l2t1c9"/>
          <title>CAPUT IX.</title>
          <questionTitle>Quod formaliter et non materialiter unitur anima, et quod ipsa est primus
            actus hujus corporis et non cujuslibet.</questionTitle>
          <hasWitnesses>
            <witness ref="#B5">
              <folio>206</folio>
              <folio>207</folio>
              <folio>208</folio>
            </witness>
          </hasWitnesses>
        </item>
        <item id="admda-l2t1c10">
          <fileName filestem="admda-l2t1c10"/>
          <title>CAPUT X.</title>
          <questionTitle>De enumeratione potentiarum principalium quae sunt potentiae
            animae.</questionTitle>
          <hasWitnesses>
            <witness ref="#B5">
              <folio>208</folio>
              <folio>209</folio>
            </witness>
          </hasWitnesses>
        </item>
        <item id="admda-l2t1c11">
          <fileName filestem="admda-l2t1c11"/>
          <title>CAPUT XI.</title>
          <questionTitle>Ex quibus partibus componitur anima, et eadem est ratio animae et
            figurae.</questionTitle>
          <hasWitnesses>
            <witness ref="#B5">
              <folio>209</folio>
              <folio>210</folio>
              <folio>211</folio>
              <folio>212</folio>
              <folio>213</folio>
            </witness>
          </hasWitnesses>
        </item>
      </div>
      <div id="admda-l2t2">
        <head>Liber II, Tractatus II</head>
        <questionTitle>DE POTENTIIS ANIMAE VEGETABILIS SIGILLATIM.</questionTitle>
        <item id="admda-l2t2c1">
          <fileName filestem="admda-l2t2c1"/>
          <title>CAPUT I.</title>
          <questionTitle>De ordine procedendi, et quot sint et quae potentiae animae
            vegetabilis.</questionTitle>
          <hasWitnesses>
            <witness ref="#B5">
              <folio>214</folio>
              <folio>215</folio>
              <folio>216</folio>
            </witness>
          </hasWitnesses>
        </item>
        <item id="admda-l2t2c2">
          <fileName filestem="admda-l2t2c2"/>
          <title>CAPUT II.</title>
          <questionTitle>Qualiter anima est viventis corporis causa et principium.</questionTitle>
          <hasWitnesses>
            <witness ref="#B5">
              <folio>216</folio>
              <folio>217</folio>
            </witness>
          </hasWitnesses>
        </item>
        <item id="admda-l2t2c3">
          <fileName filestem="admda-l2t2c3"/>
          <title>CAPUT III.</title>
          <questionTitle>De improbatione erroris Empedoclis circa motum et causam
            nutrimenti.</questionTitle>
          <hasWitnesses>
            <witness ref="#B5">
              <folio>217</folio>
              <folio>218</folio>
              <folio>219</folio>
            </witness>
          </hasWitnesses>
        </item>
        <item id="admda-l2t2c4">
          <fileName filestem="admda-l2t2c4"/>
          <title>CAPUT IV.</title>
          <questionTitle>De improbatione erroris eorum qui dicunt augmentum et alimentum fieri per
            virtutem ignis.</questionTitle>
          <hasWitnesses>
            <witness ref="#B5">
              <folio>219</folio>
              <folio>220</folio>
            </witness>
          </hasWitnesses>
        </item>
        <item id="admda-l2t2c5">
          <fileName filestem="admda-l2t2c5"/>
          <title>CAPUT V.</title>
          <questionTitle>De alimento quod est objectum nutritivae et vegetativae.</questionTitle>
          <hasWitnesses>
            <witness ref="#B5">
              <folio>220</folio>
              <folio>221</folio>
              <folio>222</folio>
            </witness>
          </hasWitnesses>
        </item>
        <item id="admda-l2t2c6">
          <fileName filestem="admda-l2t2c6"/>
          <title>CAPUT VI.</title>
          <questionTitle>De officiis nutritivae et augmentativae.</questionTitle>
          <hasWitnesses>
            <witness ref="#B5">
              <folio>222</folio>
              <folio>223</folio>
              <folio>224</folio>
            </witness>
          </hasWitnesses>
        </item>
        <item id="admda-l2t2c7">
          <fileName filestem="admda-l2t2c7"/>
          <title>CAPUT VII.</title>
          <questionTitle>De officiis virtutis generativae.</questionTitle>
          <hasWitnesses>
            <witness ref="#B5">
              <folio>224</folio>
              <folio>225</folio>
              <folio>226</folio>
            </witness>
          </hasWitnesses>
        </item>
        <item id="admda-l2t2c8">
          <fileName filestem="admda-l2t2c8"/>
          <title>CAPUT VIII.</title>
          <questionTitle>Et est digressio declarans quatuor virtutes materiales dictis tribus
            virtutibus deservientes.</questionTitle>
          <hasWitnesses>
            <witness ref="#B5">
              <folio>226</folio>
              <folio>227</folio>
            </witness>
          </hasWitnesses>
        </item>
        <item id="admda-l2t2c9">
          <fileName filestem="admda-l2t2c9"/>
          <title>CAPUT IX.</title>
          <questionTitle>De comparatione trium virtutum animae vegetabilis ad invicem et ad seipsam
            animam vegetabilem.</questionTitle>
          <hasWitnesses>
            <witness ref="#B5">
              <folio>228</folio>
              <folio>229</folio>
            </witness>
          </hasWitnesses>
        </item>
        <item id="admda-l2t2c10">
          <fileName filestem="admda-l2t2c10"/>
          <title>CAPUT X.</title>
          <questionTitle>De duplici motore nutrimenti.</questionTitle>
          <hasWitnesses>
            <witness ref="#B5">
              <folio>229</folio>
            </witness>
          </hasWitnesses>
        </item>
      </div>
      <div id="admda-l2t3">
        <head>Liber II, Tractatus III</head>
        <questionTitle>DE SENSIBUS</questionTitle>
        <item id="admda-l2t3c1">
          <fileName filestem="admda-l2t3c1"/>
          <title>CAPUT I.</title>
          <questionTitle>In quo genere potentiae sit potentia sensitiva.</questionTitle>
          <hasWitnesses>
            <witness ref="#B5">
              <folio>230</folio>
              <folio>231</folio>
              <folio>232</folio>
              <folio>233</folio>
            </witness>
          </hasWitnesses>
        </item>
        <item id="admda-l2t3c2">
          <fileName filestem="admda-l2t3c2"/>
          <title>CAPUT II.</title>
          <questionTitle>De distinctionibus potentiae passivae in apprehendendo.</questionTitle>
          <hasWitnesses>
            <witness ref="#B5">
              <folio>233</folio>
              <folio>234</folio>
              <folio>235</folio>
            </witness>
          </hasWitnesses>
        </item>
        <item id="admda-l2t3c3">
          <fileName filestem="admda-l2t3c3"/>
          <title>CAPUT III.</title>
          <questionTitle>De adaptatione dictae distinctionis potentiae ad potentiam
            sensitivam.</questionTitle>
          <hasWitnesses>
            <witness ref="#B5">
              <folio>235</folio>
              <folio>236</folio>
            </witness>
          </hasWitnesses>
        </item>
        <item id="admda-l2t3c4">
          <fileName filestem="admda-l2t3c4"/>
          <title>CAPUT IV.</title>
          <questionTitle>Et est digressio declarans gradus abstractionis et modum.</questionTitle>
          <hasWitnesses>
            <witness ref="#B5">
              <folio>237</folio>
              <folio>238</folio>
            </witness>
          </hasWitnesses>
        </item>
        <item id="admda-l2t3c5">
          <fileName filestem="admda-l2t3c5"/>
          <title>CAPUT V.</title>
          <questionTitle>De sensatis in communi quae sunt per se et proprie, et secundum se et
            commune, et per accidens.</questionTitle>
          <hasWitnesses>
            <witness ref="#B5">
              <folio>238</folio>
              <folio>239</folio>
              <folio>240</folio>
            </witness>
          </hasWitnesses>
        </item>
        <item id="admda-l2t3c6">
          <fileName filestem="admda-l2t3c6"/>
          <title>CAPUT VI.</title>
          <questionTitle>Et est digressio declarans utrum sit aliquod movens unum sit in
            sensibilibus : et est de duplici esse sensibilis quod fit in materia et in
            abstractione.</questionTitle>
          <hasWitnesses>
            <witness ref="#B5">
              <folio>240</folio>
              <folio>241</folio>
              <folio>242</folio>
              <folio>243</folio>
              <folio>244</folio>
            </witness>
          </hasWitnesses>
        </item>
        <item id="admda-l2t3c7">
          <fileName filestem="admda-l2t3c7"/>
          <title>CAPUT VII.</title>
          <questionTitle>De visibili quod est color, qualiter secundum actum lucidi movet
            visum.</questionTitle>
          <hasWitnesses>
            <witness ref="#B5">
              <folio>244</folio>
              <folio>245</folio>
              <folio>246</folio>
              <folio>247</folio>
            </witness>
          </hasWitnesses>
        </item>
        <item id="admda-l2t3c8">
          <fileName filestem="admda-l2t3c8"/>
          <title>CAPUT VIII.</title>
          <questionTitle>De natura diaphani et qualiter lumen est actus ejus.</questionTitle>
          <hasWitnesses>
            <witness ref="#B5">
              <folio>247</folio>
              <folio>248</folio>
            </witness>
          </hasWitnesses>
        </item>
        <item id="admda-l2t3c9">
          <fileName filestem="admda-l2t3c9"/>
          <title>CAPUT IX.</title>
          <questionTitle>De improbatione opinionis Democriti, qui dixit lumen esse defluxum
            corporis.</questionTitle>
          <hasWitnesses>
            <witness ref="#B5">
              <folio>248</folio>
              <folio>249</folio>
              <folio>250</folio>
            </witness>
          </hasWitnesses>
        </item>
        <item id="admda-l2t3c10">
          <fileName filestem="admda-l2t3c10"/>
          <title>CAPUT X.</title>
          <questionTitle>Et est digressio declarans errorem eorum qui dicunt lumen esse corpus
            indivisibile.</questionTitle>
          <hasWitnesses>
            <witness ref="#B5">
              <folio>250</folio>
              <folio>251</folio>
              <folio>252</folio>
              <folio>253</folio>
            </witness>
          </hasWitnesses>
        </item>
        <item id="admda-l2t3c11">
          <fileName filestem="admda-l2t3c11"/>
          <title>CAPUT XI.</title>
          <questionTitle>Et est digressio dicens defectum aliarum quatuor opinionum superius
            enumeratarum de luce et lumine.</questionTitle>
          <hasWitnesses>
            <witness ref="#B5">
              <folio>253</folio>
              <folio>254</folio>
              <folio>255</folio>
            </witness>
          </hasWitnesses>
        </item>
        <item id="admda-l2t3c12">
          <fileName filestem="admda-l2t3c12"/>
          <title>CAPUT XII.</title>
          <questionTitle>Et est digressio declarans veram sententiam de luce et de lumine et de
            natura.</questionTitle>
          <hasWitnesses>
            <witness ref="#B5">
              <folio>255</folio>
              <folio>256</folio>
            </witness>
          </hasWitnesses>
        </item>
        <item id="admda-l2t3c13">
          <fileName filestem="admda-l2t3c13"/>
          <title>CAPUT XIII.</title>
          <questionTitle>De medio visus, et quot modis dicatur visibile : in quo etiam est de his
            qui aspiciunt lumen.</questionTitle>
          <hasWitnesses>
            <witness ref="#B5">
              <folio>256</folio>
              <folio>257</folio>
              <folio>258</folio>
            </witness>
          </hasWitnesses>
        </item>
        <item id="admda-l2t3c14">
          <fileName filestem="admda-l2t3c14"/>
          <title>CAPUT XIV.</title>
          <questionTitle>Qualiter color in lumine videtur, et non sine lumine, et de quantitate
            visorum.</questionTitle>
          <hasWitnesses>
            <witness ref="#B5">
              <folio>258</folio>
              <folio>259</folio>
              <folio>260</folio>
              <folio>261</folio>
            </witness>
          </hasWitnesses>
        </item>
        <item id="admda-l2t3c15">
          <fileName filestem="admda-l2t3c15"/>
          <title>CAPUT XV.</title>
          <questionTitle>Quare per vacuum non potest videri, et de visu in speculo.</questionTitle>
          <hasWitnesses>
            <witness ref="#B5">
              <folio>261</folio>
              <folio>262</folio>
            </witness>
          </hasWitnesses>
        </item>
        <item id="admda-l2t3c16">
          <fileName filestem="admda-l2t3c16"/>
          <title>CAPUT XVI.</title>
          <questionTitle>De visu lucentium.</questionTitle>
          <hasWitnesses>
            <witness ref="#B5">
              <folio>262</folio>
              <folio>263</folio>
            </witness>
          </hasWitnesses>
        </item>
        <item id="admda-l2t3c17">
          <fileName filestem="admda-l2t3c17"/>
          <title>CAPUT XVII.</title>
          <questionTitle>De auditu, et primo de bene sonantibus et male.</questionTitle>
          <hasWitnesses>
            <witness ref="#B5">
              <folio>263</folio>
              <folio>264</folio>
              <folio>265</folio>
            </witness>
          </hasWitnesses>
        </item>
        <item id="admda-l2t3c18">
          <fileName filestem="admda-l2t3c18"/>
          <title>CAPUT XVIII.</title>
          <questionTitle>Qualiter sonus generatur in aere et aqua.</questionTitle>
          <hasWitnesses>
            <witness ref="#B5">
              <folio>265</folio>
              <folio>266</folio>
              <folio>267</folio>
            </witness>
          </hasWitnesses>
        </item>
        <item id="admda-l2t3c19">
          <fileName filestem="admda-l2t3c19"/>
          <title>CAPUT XIX.</title>
          <questionTitle>De echo qui est sonus reflexus.</questionTitle>
          <hasWitnesses>
            <witness ref="#B5">
              <folio>267</folio>
              <folio>268</folio>
              <folio>269</folio>
            </witness>
          </hasWitnesses>
        </item>
        <item id="admda-l2t3c20">
          <fileName filestem="admda-l2t3c20"/>
          <title>CAPUT XX.</title>
          <questionTitle>Qualiter sonus venit ad auditum auris, et qualiter auris connaturalitatem
            habeat ad audiendum.</questionTitle>
          <hasWitnesses>
            <witness ref="#B5">
              <folio>269</folio>
              <folio>270</folio>
            </witness>
          </hasWitnesses>
        </item>
        <item id="admda-l2t3c21">
          <fileName filestem="admda-l2t3c21"/>
          <title>CAPUT XXI.</title>
          <questionTitle>De differentiis sonorum quae non fiunt nisi in sono secundum actum
            facto.</questionTitle>
          <hasWitnesses>
            <witness ref="#B5">
              <folio>270</folio>
              <folio>271</folio>
            </witness>
          </hasWitnesses>
        </item>
        <item id="admda-l2t3c22">
          <fileName filestem="admda-l2t3c22"/>
          <title>CAPUT XXII.</title>
          <questionTitle>De voce qualiter fiat.</questionTitle>
          <hasWitnesses>
            <witness ref="#B5">
              <folio>271</folio>
              <folio>272</folio>
              <folio>273</folio>
            </witness>
          </hasWitnesses>
        </item>
        <item id="admda-l2t3c23">
          <fileName filestem="admda-l2t3c23"/>
          <title>CAPUT XXIII.</title>
          <questionTitle>Quare homo non bene odorat, sed bene tangit, et ideo
            prudens.</questionTitle>
          <hasWitnesses>
            <witness ref="#B5">
              <folio>273</folio>
              <folio>274</folio>
              <folio>275</folio>
            </witness>
          </hasWitnesses>
        </item>
        <item id="admda-l2t3c24">
          <fileName filestem="admda-l2t3c24"/>
          <title>CAPUT XXIV.</title>
          <questionTitle>Qualiter odorum differentiae per analogiam ad differentias saporum
            accipiuntur.</questionTitle>
          <hasWitnesses>
            <witness ref="#B5">
              <folio>275</folio>
              <folio>276</folio>
            </witness>
          </hasWitnesses>
        </item>
        <item id="admda-l2t3c25">
          <fileName filestem="admda-l2t3c25"/>
          <title>CAPUT XXV.</title>
          <questionTitle>Qualiter odor se habet ad olfactum et ad medium, et utrum sit evaporatio
            fumalis.</questionTitle>
          <hasWitnesses>
            <witness ref="#B5">
              <folio>276</folio>
              <folio>277</folio>
              <folio>278</folio>
            </witness>
          </hasWitnesses>
        </item>
        <item id="admda-l2t3c26">
          <fileName filestem="admda-l2t3c26"/>
          <title>CAPUT XXVI.</title>
          <questionTitle>Qualiter olfactus est in respirantibus, et in non
            respirantibus.</questionTitle>
          <hasWitnesses>
            <witness ref="#B5">
              <folio>278</folio>
              <folio>279</folio>
              <folio>280</folio>
            </witness>
          </hasWitnesses>
        </item>
        <item id="admda-l2t3c27">
          <fileName filestem="admda-l2t3c27"/>
          <title>CAPUT XXVII.</title>
          <questionTitle>De gustu secundum quod est in medio secundum esse materiale
            ipsius.</questionTitle>
          <hasWitnesses>
            <witness ref="#B5">
              <folio>280</folio>
              <folio>281</folio>
            </witness>
          </hasWitnesses>
        </item>
        <item id="admda-l2t3c28">
          <fileName filestem="admda-l2t3c28"/>
          <title>CAPUT XXVIII.</title>
          <questionTitle>Qualiter saporis differentiae se habent ad gustum, et e
            converso.</questionTitle>
          <hasWitnesses>
            <witness ref="#B5">
              <folio>281</folio>
              <folio>282</folio>
            </witness>
          </hasWitnesses>
        </item>
        <item id="admda-l2t3c29">
          <fileName filestem="admda-l2t3c29"/>
          <title>CAPUT XXIX.</title>
          <questionTitle>De differentiis saporum secundum speciem, et qualiter se habent ad
            gustum.</questionTitle>
          <hasWitnesses>
            <witness ref="#B5">
              <folio>283</folio>
              <folio>284</folio>
            </witness>
          </hasWitnesses>
        </item>
        <item id="admda-l2t3c30">
          <fileName filestem="admda-l2t3c30"/>
          <title>CAPUT XXX.</title>
          <questionTitle>De tactu, utrum sit unus an plures.</questionTitle>
          <hasWitnesses>
            <witness ref="#B5">
              <folio>284</folio>
              <folio>285</folio>
            </witness>
          </hasWitnesses>
        </item>
        <item id="admda-l2t3c31">
          <fileName filestem="admda-l2t3c31"/>
          <title>CAPUT XXXI.</title>
          <questionTitle>Quod caro non est organum tactus.</questionTitle>
          <hasWitnesses>
            <witness ref="#B5">
              <folio>285</folio>
              <folio>286</folio>
              <folio>287</folio>
            </witness>
          </hasWitnesses>
        </item>
        <item id="admda-l2t3c32">
          <fileName filestem="admda-l2t3c32"/>
          <title>CAPUT XXXII.</title>
          <questionTitle>Utrum tactus indigeat aliquo medio extrinseco.</questionTitle>
          <hasWitnesses>
            <witness ref="#B5">
              <folio>287</folio>
              <folio>288</folio>
              <folio>289</folio>
            </witness>
          </hasWitnesses>
        </item>
        <item id="admda-l2t3c33">
          <fileName filestem="admda-l2t3c33"/>
          <title>CAPUT XXXIII.</title>
          <questionTitle>Et est digressio dicens intentiones Alexandri, Themistii, Averrois et
            Avicennae.</questionTitle>
          <hasWitnesses>
            <witness ref="#B5">
              <folio>289</folio>
              <folio>290</folio>
            </witness>
          </hasWitnesses>
        </item>
        <item id="admda-l2t3c34">
          <fileName filestem="admda-l2t3c34"/>
          <title>CAPUT XXXIV.</title>
          <questionTitle>De medio tactus, quid sit, et quot modis dicatur.</questionTitle>
          <hasWitnesses>
            <witness ref="#B5">
              <folio>290</folio>
              <folio>291</folio>
            </witness>
          </hasWitnesses>
        </item>
        <item id="admda-l2t3c35">
          <fileName filestem="admda-l2t3c35"/>
          <title>CAPUT XXXV.</title>
          <questionTitle>Qualiter se habet tactus ad tangibilia.</questionTitle>
          <hasWitnesses>
            <witness ref="#B5">
              <folio>291</folio>
              <folio>292</folio>
            </witness>
          </hasWitnesses>
        </item>
      </div>
      <div id="admda-l2t4">
        <head>Liber II, Tractatus IV</head>
        <questionTitle>DE COMMUNIBUS SENSUUM</questionTitle>
        <item id="admda-l2t4c1">
          <fileName filestem="admda-l2t4c1"/>
          <title>CAPUT I.</title>
          <questionTitle>Quod omnis sensus est susceptivus specierum sensibilium.</questionTitle>
          <hasWitnesses>
            <witness ref="#B5">
              <folio>293</folio>
              <folio>294</folio>
            </witness>
          </hasWitnesses>
        </item>
        <item id="admda-l2t4c2">
          <fileName filestem="admda-l2t4c2"/>
          <title>CAPUT II.</title>
          <questionTitle>Utrum aliquid non habens sensum patiatur a sensibus.</questionTitle>
          <hasWitnesses>
            <witness ref="#B5">
              <folio>294</folio>
              <folio>295</folio>
            </witness>
          </hasWitnesses>
        </item>
        <item id="admda-l2t4c3">
          <fileName filestem="admda-l2t4c3"/>
          <title>CAPUT III.</title>
          <questionTitle>In quo est probatio, quod non est sensus praeter quinque per naturam
            mediorum.</questionTitle>
          <hasWitnesses>
            <witness ref="#B5">
              <folio>295</folio>
              <folio>296</folio>
              <folio>297</folio>
            </witness>
          </hasWitnesses>
        </item>
        <item id="admda-l2t4c4">
          <fileName filestem="admda-l2t4c4"/>
          <title>CAPUT IV.</title>
          <questionTitle>In quo probatur non esse nisi quinque sensus per naturam
            organorum.</questionTitle>
          <hasWitnesses>
            <witness ref="#B5">
              <folio>297</folio>
              <folio>298</folio>
              <folio>299</folio>
            </witness>
          </hasWitnesses>
        </item>
        <item id="admda-l2t4c5">
          <fileName filestem="admda-l2t4c5"/>
          <title>CAPUT V.</title>
          <questionTitle>In quo probatur, quod nullus deest sensus ab ipsis
            sensibilibus.</questionTitle>
          <hasWitnesses>
            <witness ref="#B5">
              <folio>299</folio>
              <folio>300</folio>
            </witness>
          </hasWitnesses>
        </item>
        <item id="admda-l2t4c6">
          <fileName filestem="admda-l2t4c6"/>
          <title>CAPUT VI.</title>
          <questionTitle>Quod sensatorum omnium non potest esse aliquis sensus a
            praedictis.</questionTitle>
          <hasWitnesses>
            <witness ref="#B5">
              <folio>300</folio>
              <folio>301</folio>
              <folio>302</folio>
            </witness>
          </hasWitnesses>
        </item>
        <item id="admda-l2t4c7">
          <fileName filestem="admda-l2t4c7"/>
          <title>CAPUT VII.</title>
          <questionTitle>Et est digressio declarans quinque vires animae sensibilis
            interiores.</questionTitle>
          <hasWitnesses>
            <witness ref="#B5">
              <folio>302</folio>
              <folio>303</folio>
              <folio>304</folio>
            </witness>
          </hasWitnesses>
        </item>
        <item id="admda-l2t4c8">
          <fileName filestem="admda-l2t4c8"/>
          <title>CAPUT VIII.</title>
          <questionTitle>De eo quod sensu communi nos sentimus videre et audire, et secundum alios
            operari.</questionTitle>
          <hasWitnesses>
            <witness ref="#B5">
              <folio>304</folio>
              <folio>305</folio>
              <folio>306</folio>
            </witness>
          </hasWitnesses>
        </item>
        <item id="admda-l2t4c9">
          <fileName filestem="admda-l2t4c9"/>
          <title>CAPUT IX.</title>
          <questionTitle>Qualiter sensitivum sensibileque idem actu sunt et diversa in esse, et
            qualiter correlativa.</questionTitle>
          <hasWitnesses>
            <witness ref="#B5">
              <folio>306</folio>
              <folio>307</folio>
              <folio>308</folio>
            </witness>
          </hasWitnesses>
        </item>
        <item id="admda-l2t4c10">
          <fileName filestem="admda-l2t4c10"/>
          <title>CAPUT X.</title>
          <questionTitle>De probatione sensus communis per hoc quod componit et dividit inter
            sensata diversorum sensuum.</questionTitle>
          <hasWitnesses>
            <witness ref="#B5">
              <folio>308</folio>
              <folio>309</folio>
              <folio>310</folio>
            </witness>
          </hasWitnesses>
        </item>
        <item id="admda-l2t4c11">
          <fileName filestem="admda-l2t4c11"/>
          <title>CAPUT XI.</title>
          <questionTitle>In quo declaratur qualiter sensus communis est unus et indivisibilis, et
            qualiter diversus.</questionTitle>
          <hasWitnesses>
            <witness ref="#B5">
              <folio>310</folio>
              <folio>311</folio>
            </witness>
          </hasWitnesses>
        </item>
        <item id="admda-l2t4c12">
          <fileName filestem="admda-l2t4c12"/>
          <title>CAPUT XII.</title>
          <questionTitle>Et est digressio declarans qualiter sensus communis est medietas omnium
            sensuum.</questionTitle>
          <hasWitnesses>
            <witness ref="#B5">
              <folio>312</folio>
              <folio>313</folio>
            </witness>
          </hasWitnesses>
        </item>
      </div>
    </div>
    <div id="admda-l3" type="da-liber3">
      <head>Liber III</head>
      <questionTitle>QUI EST DE APPREHENSIVIS VIRIBUS DEINTUS.</questionTitle>
      <div id="admda-l3t1">
        <head>Liber III, Tractatus I</head>
        <questionTitle>DE VIRIBUS ANIMAE SENSIBILIS.</questionTitle>
        <item id="admda-l3t1c1">
          <fileName filestem="admda-l3t1c1"/>
          <title>CAPUT I.</title>
          <questionTitle>Et est digressio declarans libri intentionem, et de
            imaginatione.</questionTitle>
          <hasWitnesses>
            <witness ref="#B5">
              <folio>315</folio>
              <folio>316</folio>
            </witness>
          </hasWitnesses>
        </item>
        <item id="admda-l3t1c2">
          <fileName filestem="admda-l3t1c2"/>
          <title>CAPUT II.</title>
          <questionTitle>Et est digressio declarans ea quae conveniunt ex
            aestimatione.</questionTitle>
          <hasWitnesses>
            <witness ref="#B5">
              <folio>317</folio>
              <folio>318</folio>
            </witness>
          </hasWitnesses>
        </item>
        <item id="admda-l3t1c3">
          <fileName filestem="admda-l3t1c3"/>
          <title>CAPUT III.</title>
          <questionTitle>Et est digressio declarans naturam phantasiae.</questionTitle>
          <hasWitnesses>
            <witness ref="#B5">
              <folio>318</folio>
              <folio>319</folio>
            </witness>
          </hasWitnesses>
        </item>
        <item id="admda-l3t1c4">
          <fileName filestem="admda-l3t1c4"/>
          <title>CAPUT IV.</title>
          <questionTitle>Et est digressio declarans quod omnes vires animae sunt organicae, et agunt
            mediante corpore.</questionTitle>
          <hasWitnesses>
            <witness ref="#B5">
              <folio>319</folio>
              <folio>320</folio>
            </witness>
          </hasWitnesses>
        </item>
        <item id="admda-l3t1c5">
          <fileName filestem="admda-l3t1c5"/>
          <title>CAPUT V.</title>
          <questionTitle>De improbatione erroris Antiquorum qui dixerunt quod intelligere et sentire
            sunt idem.</questionTitle>
          <hasWitnesses>
            <witness ref="#B5">
              <folio>321</folio>
              <folio>322</folio>
            </witness>
          </hasWitnesses>
        </item>
        <item id="admda-l3t1c6">
          <fileName filestem="admda-l3t1c6"/>
          <title>CAPUT VI.</title>
          <questionTitle>Quod imaginatio vel phantasia, neque sensus sunt, neque opinio cum
            sensu.</questionTitle>
          <hasWitnesses>
            <witness ref="#B5">
              <folio>322</folio>
              <folio>323</folio>
            </witness>
          </hasWitnesses>
        </item>
        <item id="admda-l3t1c7">
          <fileName filestem="admda-l3t1c7"/>
          <title>CAPUT VII.</title>
          <questionTitle>Quare imaginatio vel phantasia, neque sensus sunt, neque opinio cum
            sensu.</questionTitle>
          <hasWitnesses>
            <witness ref="#B5">
              <folio>323</folio>
              <folio>324</folio>
              <folio>325</folio>
              <folio>326</folio>
            </witness>
          </hasWitnesses>
        </item>
        <item id="admda-l3t1c8">
          <fileName filestem="admda-l3t1c8"/>
          <title>CAPUT VIII.</title>
          <questionTitle>Quid sit phantasia secundum veritatem, prout communiter agitur de
            imaginatione phantasiae.</questionTitle>
          <hasWitnesses>
            <witness ref="#B5">
              <folio>326</folio>
              <folio>327</folio>
            </witness>
          </hasWitnesses>
        </item>
        <item id="admda-l3t1c9">
          <fileName filestem="admda-l3t1c9"/>
          <title>CAPUT IX.</title>
          <questionTitle>De ratione nominis phantasiae et utilitate ejus.</questionTitle>
          <hasWitnesses>
            <witness ref="#B5">
              <folio>327</folio>
              <folio>328</folio>
            </witness>
          </hasWitnesses>
        </item>
      </div>
      <div id="admda-l3t2">
        <head>Liber III, Tractatus II</head>
        <questionTitle>DE PARTE RATIONALI</questionTitle>
        <item id="admda-l3t2c1">
          <fileName filestem="admda-l3t2c1"/>
          <title>CAPUT I.</title>
          <questionTitle>Qui tractatus est qualiter intellectus possibilis est.</questionTitle>
          <hasWitnesses>
            <witness ref="#B5">
              <folio>329</folio>
              <folio>330</folio>
              <folio>331</folio>
            </witness>
          </hasWitnesses>
        </item>
        <item id="admda-l3t2c2">
          <fileName filestem="admda-l3t2c2"/>
          <title>CAPUT II.</title>
          <questionTitle>Qualiter intellectus possibilis sit natura quaedam immixta receptibilis
            omnium eorum quae sunt.</questionTitle>
          <hasWitnesses>
            <witness ref="#B5">
              <folio>332</folio>
              <folio>333</folio>
            </witness>
          </hasWitnesses>
        </item>
        <item id="admda-l3t2c3">
          <fileName filestem="admda-l3t2c3"/>
          <title>CAPUT III.</title>
          <questionTitle>Et est digressio declarans dubia quae consequuntur ex dictis de intellectu
            possibili.</questionTitle>
          <hasWitnesses>
            <witness ref="#B5">
              <folio>333</folio>
              <folio>334</folio>
              <folio>335</folio>
            </witness>
          </hasWitnesses>
        </item>
        <item id="admda-l3t2c4">
          <fileName filestem="admda-l3t2c4"/>
          <title>CAPUT IV.</title>
          <questionTitle>Et est digressio declarans opinionem Alexandri et ejus
            improbationem.</questionTitle>
          <hasWitnesses>
            <witness ref="#B5">
              <folio>335</folio>
              <folio>336</folio>
              <folio>337</folio>
            </witness>
          </hasWitnesses>
        </item>
        <item id="admda-l3t2c5">
          <fileName filestem="admda-l3t2c5"/>
          <title>CAPUT V.</title>
          <questionTitle>Et est digressio declarans opinionem Theophrasti et Themistii, et
            improbationem ejusdem.</questionTitle>
          <hasWitnesses>
            <witness ref="#B5">
              <folio>337</folio>
              <folio>338</folio>
              <folio>339</folio>
            </witness>
          </hasWitnesses>
        </item>
        <item id="admda-l3t2c6">
          <fileName filestem="admda-l3t2c6"/>
          <title>CAPUT VI.</title>
          <questionTitle>Et est digressio declarans opinionem Avempacis et Abubacher, et
            improbationem ejusdem.</questionTitle>
          <hasWitnesses>
            <witness ref="#B5">
              <folio>339</folio>
              <folio>340</folio>
            </witness>
          </hasWitnesses>
        </item>
        <item id="admda-l3t2c7">
          <fileName filestem="admda-l3t2c7"/>
          <title>CAPUT VII.</title>
          <questionTitle>Et est digressio declarans opinionem Averrois, et improbationem
            ejusdem.</questionTitle>
          <hasWitnesses>
            <witness ref="#B5">
              <folio>340</folio>
              <folio>341</folio>
              <folio>342</folio>
              <folio>343</folio>
            </witness>
          </hasWitnesses>
        </item>
        <item id="admda-l3t2c8">
          <fileName filestem="admda-l3t2c8"/>
          <title>CAPUT VIII.</title>
          <questionTitle>Et est digressio declarans opinionem eorum qui dixerunt nullam partem
            animae esse intellectualem, et errorem eorumdem.</questionTitle>
          <hasWitnesses>
            <witness ref="#B5">
              <folio>343</folio>
              <folio>344</folio>
            </witness>
          </hasWitnesses>
        </item>
        <item id="admda-l3t2c9">
          <fileName filestem="admda-l3t2c9"/>
          <title>CAPUT IX.</title>
          <questionTitle>Et est digressio declarans opinionem Avicebron, et errorem
            ejusdem.</questionTitle>
          <hasWitnesses>
            <witness ref="#B5">
              <folio>344</folio>
              <folio>345</folio>
              <folio>346</folio>
            </witness>
          </hasWitnesses>
        </item>
        <item id="admda-l3t2c10">
          <fileName filestem="admda-l3t2c10"/>
          <title>CAPUT X.</title>
          <questionTitle>Et est digressio declarans opinionem Platonis et Gregorii Nysseni, et ejus
            errorem.</questionTitle>
          <hasWitnesses>
            <witness ref="#B5">
              <folio>346</folio>
              <folio>347</folio>
            </witness>
          </hasWitnesses>
        </item>
        <item id="admda-l3t2c11">
          <fileName filestem="admda-l3t2c11"/>
          <title>CAPUT XI.</title>
          <questionTitle>Et est digressio declarans opinionem Latinorum, et errorem
            eorumdem.</questionTitle>
          <hasWitnesses>
            <witness ref="#B5">
              <folio>347</folio>
              <folio>348</folio>
              <folio>349</folio>
            </witness>
          </hasWitnesses>
        </item>
        <item id="admda-l3t2c12">
          <fileName filestem="admda-l3t2c12"/>
          <title>CAPUT XII.</title>
          <questionTitle>Et est digressio declarans veram sententiam de omnibus inductis dubiis
            Peripateticorum.</questionTitle>
          <hasWitnesses>
            <witness ref="#B5">
              <folio>349</folio>
              <folio>350</folio>
              <folio>351</folio>
              <folio>352</folio>
            </witness>
          </hasWitnesses>
        </item>
        <item id="admda-l3t2c13">
          <fileName filestem="admda-l3t2c13"/>
          <title>CAPUT XIII.</title>
          <questionTitle>Et est digressio declarans solutionem duarum quaestionum difficilium
            relictarum ex praedictis.</questionTitle>
          <hasWitnesses>
            <witness ref="#B5">
              <folio>353</folio>
              <folio>354</folio>
            </witness>
          </hasWitnesses>
        </item>
        <item id="admda-l3t2c14">
          <fileName filestem="admda-l3t2c14"/>
          <title>CAPUT XIV.</title>
          <questionTitle>Et est digressio declarans propter quid intellectus est separatus et
            immixtus.</questionTitle>
          <hasWitnesses>
            <witness ref="#B5">
              <folio>354</folio>
              <folio>355</folio>
              <folio>356</folio>
            </witness>
          </hasWitnesses>
        </item>
        <item id="admda-l3t2c15">
          <fileName filestem="admda-l3t2c15"/>
          <title>CAPUT XV.</title>
          <questionTitle>Quo probatur quod intellectus non est mixtus corpori per hoc quod sua
            passibilitas non est similis passibilitati sensus.</questionTitle>
          <hasWitnesses>
            <witness ref="#B5">
              <folio>356</folio>
              <folio>357</folio>
              <folio>358</folio>
            </witness>
          </hasWitnesses>
        </item>
        <item id="admda-l3t2c16">
          <fileName filestem="admda-l3t2c16"/>
          <title>CAPUT XVI.</title>
          <questionTitle>Quod unus intellectus est qui distinguit inter sensibile et
            intelligibile.</questionTitle>
          <hasWitnesses>
            <witness ref="#B5">
              <folio>358</folio>
              <folio>359</folio>
            </witness>
          </hasWitnesses>
        </item>
        <item id="admda-l3t2c17">
          <fileName filestem="admda-l3t2c17"/>
          <title>CAPUT XVII.</title>
          <questionTitle>Qualiter intellectus est subjectum receptionis et non transmutationis, et
            qualiter intelligit se.</questionTitle>
          <hasWitnesses>
            <witness ref="#B5">
              <folio>361</folio>
              <folio>362</folio>
              <folio>363</folio>
            </witness>
          </hasWitnesses>
        </item>
        <item id="admda-l3t2c18">
          <fileName filestem="admda-l3t2c18"/>
          <title>CAPUT XVIII.</title>
          <questionTitle>De natura intellectus agentis, et qualiter anima est
            composita.</questionTitle>
          <hasWitnesses>
            <witness ref="#B5">
              <folio>363</folio>
              <folio>364</folio>
              <folio>365</folio>
              <folio>366</folio>
            </witness>
          </hasWitnesses>
        </item>
        <item id="admda-l3t2c19">
          <fileName filestem="admda-l3t2c19"/>
          <title>CAPUT XIX.</title>
          <questionTitle>De comparatione intellectus possibilis et agentis et
            speculativi.</questionTitle>
          <hasWitnesses>
            <witness ref="#B5">
              <folio>366</folio>
              <folio>367</folio>
            </witness>
          </hasWitnesses>
        </item>
      </div>
      <div id="admda-l3t3">
        <head>Liber III, Tractatus III</head>
        <questionTitle>DE ACTIONIBUS INTELLECTUS POSSIBILIS.</questionTitle>
        <item id="admda-l3t3c1">
          <fileName filestem="admda-l3t3c1"/>
          <title>CAPUT I.</title>
          <questionTitle>De intellectu indivisibilium diversimode dictorum.</questionTitle>
          <hasWitnesses>
            <witness ref="#B5">
              <folio>368</folio>
              <folio>369</folio>
              <folio>370</folio>
              <folio>371</folio>
            </witness>
          </hasWitnesses>
        </item>
        <item id="admda-l3t3c2">
          <fileName filestem="admda-l3t3c2"/>
          <title>CAPUT II.</title>
          <questionTitle>Et quis intellectus est semper verus : et quis aliquando verus, aliquando
            falsus : et quod actus sensus et intellectus sunt actus perfecti et motus
            simplices.</questionTitle>
          <hasWitnesses>
            <witness ref="#B5">
              <folio>372</folio>
              <folio>373</folio>
            </witness>
          </hasWitnesses>
        </item>
        <item id="admda-l3t3c3">
          <fileName filestem="admda-l3t3c3"/>
          <title>CAPUT III.</title>
          <questionTitle>Quod est idem intellectus componens et dividens intelligibilia, sicut est
            idem sensus communis.</questionTitle>
          <hasWitnesses>
            <witness ref="#B5">
              <folio>373</folio>
              <folio>374</folio>
              <folio>375</folio>
            </witness>
          </hasWitnesses>
        </item>
        <item id="admda-l3t3c4">
          <fileName filestem="admda-l3t3c4"/>
          <title>CAPUT IV.</title>
          <questionTitle>Quod eadem est analogia phantasmatum ad intellectum, quae est sensibilium
            ad sensitivum.</questionTitle>
          <hasWitnesses>
            <witness ref="#B5">
              <folio>375</folio>
              <folio>376</folio>
            </witness>
          </hasWitnesses>
        </item>
        <item id="admda-l3t3c5">
          <fileName filestem="admda-l3t3c5"/>
          <title>CAPUT V.</title>
          <questionTitle>De intellectu mathematicorum et divinorum.</questionTitle>
          <hasWitnesses>
            <witness ref="#B5">
              <folio>377</folio>
            </witness>
          </hasWitnesses>
        </item>
        <item id="admda-l3t3c6">
          <fileName filestem="admda-l3t3c6"/>
          <title>CAPUT VI.</title>
          <questionTitle>Qualiter intelliguntur divina quae sunt separata : in quo est digressio
            declarans hoc quod dixit Alexander, et improbationem ejusdem erroris.</questionTitle>
          <hasWitnesses>
            <witness ref="#B5">
              <folio>378</folio>
              <folio>379</folio>
              <folio>380</folio>
            </witness>
          </hasWitnesses>
        </item>
        <item id="admda-l3t3c7">
          <fileName filestem="admda-l3t3c7"/>
          <title>CAPUT VII.</title>
          <questionTitle>Et est digressio declarans opinionem Themistii et Theophrasti in solutione
            quaestionis inductae.</questionTitle>
          <hasWitnesses>
            <witness ref="#B5">
              <folio>380</folio>
              <folio>381</folio>
            </witness>
          </hasWitnesses>
        </item>
        <item id="admda-l3t3c8">
          <fileName filestem="admda-l3t3c8"/>
          <title>CAPUT VIII.</title>
          <questionTitle>Et est digressio de solutionem quaestionis Avempacis et Alfarabii in quo
            erraverunt.</questionTitle>
          <hasWitnesses>
            <witness ref="#B5">
              <folio>381</folio>
              <folio>382</folio>
              <folio>383</folio>
            </witness>
          </hasWitnesses>
        </item>
        <item id="admda-l3t3c9">
          <fileName filestem="admda-l3t3c9"/>
          <title>CAPUT IX.</title>
          <questionTitle>Et est digressio qualiter Avicenna et Algazel solvunt inductam quaestionem,
            et quaestio dubitationis est in dictis eo rumeorum.</questionTitle>
          <hasWitnesses>
            <witness ref="#B5">
              <folio>383</folio>
              <folio>384</folio>
            </witness>
          </hasWitnesses>
        </item>
        <item id="admda-l3t3c10">
          <fileName filestem="admda-l3t3c10"/>
          <title>CAPUT X.</title>
          <questionTitle>Et est digressio declarans quorumdam modernorum solutionem.</questionTitle>
          <hasWitnesses>
            <witness ref="#B5">
              <folio>384</folio>
              <folio>385</folio>
            </witness>
          </hasWitnesses>
        </item>
        <item id="admda-l3t3c11">
          <fileName filestem="admda-l3t3c11"/>
          <title>CAPUT XI.</title>
          <questionTitle>Et est digressio declarans veram causam et modum conjunctionis intellectus
            agentis nobiscum.</questionTitle>
          <hasWitnesses>
            <witness ref="#B5">
              <folio>385</folio>
              <folio>386</folio>
              <folio>387</folio>
              <folio>388</folio>
            </witness>
          </hasWitnesses>
        </item>
        <item id="admda-l3t3c12">
          <fileName filestem="admda-l3t3c12"/>
          <title>CAPUT XII.</title>
          <questionTitle>Quomodo anima est omnia quodammodo quae sunt.</questionTitle>
          <hasWitnesses>
            <witness ref="#B5">
              <folio>388</folio>
              <folio>389</folio>
            </witness>
          </hasWitnesses>
        </item>
        <item id="admda-l3t3c13">
          <fileName filestem="admda-l3t3c13"/>
          <title>CAPUT XIII.</title>
          <questionTitle>Et est digressio declarans quod anima non moritur morte corporis, et quod
            non fuit ante corpus.</questionTitle>
          <hasWitnesses>
            <witness ref="#B5">
              <folio>390</folio>
              <folio>391</folio>
              <folio>392</folio>
            </witness>
          </hasWitnesses>
        </item>
        <item id="admda-l3t3c14">
          <fileName filestem="admda-l3t3c14"/>
          <title>CAPUT XIV.</title>
          <questionTitle>Et est digressio declarans errorem eorum qui dicunt de omnibus animabus
            tantum unam remanere post mortem.</questionTitle>
          <hasWitnesses>
            <witness ref="#B5">
              <folio>392</folio>
              <folio>393</folio>
            </witness>
          </hasWitnesses>
        </item>
      </div>
      <div id="admda-l3t4">
        <head>Liber III, Tractatus IV</head>
        <questionTitle>DE MOTIVIS VIRIBUS.</questionTitle>
        <item id="admda-l3t4c1">
          <fileName filestem="admda-l3t4c1"/>
          <title>CAPUT I.</title>
          <questionTitle>Quae pars animae sit motiva.</questionTitle>
          <hasWitnesses>
            <witness ref="#B5">
              <folio>394</folio>
              <folio>395</folio>
              <folio>396</folio>
            </witness>
          </hasWitnesses>
        </item>
        <item id="admda-l3t4c2">
          <fileName filestem="admda-l3t4c2"/>
          <title>CAPUT II.</title>
          <questionTitle>Quod vegetativum secundum se et sensitivum secundum se non sunt motiva
            secundum locum.</questionTitle>
          <hasWitnesses>
            <witness ref="#B5">
              <folio>396</folio>
              <folio>397</folio>
            </witness>
          </hasWitnesses>
        </item>
        <item id="admda-l3t4c3">
          <fileName filestem="admda-l3t4c3"/>
          <title>CAPUT III.</title>
          <questionTitle>Quod nec intellectivus nec operativus secundum se sunt causa motus secundum
            locum, sed duo horum vel tria simul.</questionTitle>
          <hasWitnesses>
            <witness ref="#B5">
              <folio>397</folio>
              <folio>398</folio>
              <folio>399</folio>
            </witness>
          </hasWitnesses>
        </item>
        <item id="admda-l3t4c4">
          <fileName filestem="admda-l3t4c4"/>
          <title>CAPUT IV.</title>
          <questionTitle>De differentiis intellectus practici et speculativi.</questionTitle>
          <hasWitnesses>
            <witness ref="#B5">
              <folio>399</folio>
              <folio>400</folio>
              <folio>401</folio>
            </witness>
          </hasWitnesses>
        </item>
        <item id="admda-l3t4c5">
          <fileName filestem="admda-l3t4c5"/>
          <title>CAPUT V.</title>
          <questionTitle>Qualiter unum specie sunt moventia et plura secundum
            substantiam.</questionTitle>
          <hasWitnesses>
            <witness ref="#B5">
              <folio>401</folio>
              <folio>402</folio>
            </witness>
          </hasWitnesses>
        </item>
        <item id="admda-l3t4c6">
          <fileName filestem="admda-l3t4c6"/>
          <title>CAPUT VI.</title>
          <questionTitle>Quod intellectus semper est rectus, ille scilicet qui est movens :
            phantasia autem et appetitus recta et non recta.</questionTitle>
          <hasWitnesses>
            <witness ref="#B5">
              <folio>402</folio>
              <folio>403</folio>
              <folio>404</folio>
            </witness>
          </hasWitnesses>
        </item>
        <item id="admda-l3t4c7">
          <fileName filestem="admda-l3t4c7"/>
          <title>CAPUT VII.</title>
          <questionTitle>Quod omnia moventia sunt unum specie et diversa numero, et ad quem numerum,
            et ad quam speciem.</questionTitle>
          <hasWitnesses>
            <witness ref="#B5">
              <folio>404</folio>
              <folio>405</folio>
            </witness>
          </hasWitnesses>
        </item>
        <item id="admda-l3t4c8">
          <fileName filestem="admda-l3t4c8"/>
          <title>CAPUT VIII.</title>
          <questionTitle>Qualiter est motus processivus secundum quod fit a motore immobili secundum
            locum.</questionTitle>
          <hasWitnesses>
            <witness ref="#B5">
              <folio>405</folio>
              <folio>406</folio>
            </witness>
          </hasWitnesses>
        </item>
        <item id="admda-l3t4c9">
          <fileName filestem="admda-l3t4c9"/>
          <title>CAPUT IX.</title>
          <questionTitle>Quid est movens in animalibus perfectis, et quando unum movet aliud, et e
            converso.</questionTitle>
          <hasWitnesses>
            <witness ref="#B5">
              <folio>406</folio>
              <folio>407</folio>
              <folio>408</folio>
            </witness>
          </hasWitnesses>
        </item>
        <item id="admda-l3t4c10">
          <fileName filestem="admda-l3t4c10"/>
          <title>CAPUT X.</title>
          <questionTitle>Et est digressio declarans suas diversitates secundum Platonicos et
            Theologos.</questionTitle>
          <hasWitnesses>
            <witness ref="#B5">
              <folio>409</folio>
              <folio>410</folio>
              <folio>411</folio>
            </witness>
          </hasWitnesses>
        </item>
      </div>
      <div id="admda-l3t5">
        <head>Liber III, Tractatus V</head>
        <questionTitle>DE COMPARATIONE POTENTIARUM ANIMAE AD ANIMATA.</questionTitle>
        <item id="admda-l3t5c1">
          <fileName filestem="admda-l3t5c1"/>
          <title>CAPUT I.</title>
          <questionTitle>Quod omne animatum habet vegetabile, sed non necessario habet
            sensum.</questionTitle>
          <hasWitnesses>
            <witness ref="#B5">
              <folio>412</folio>
              <folio>413</folio>
              <folio>414</folio>
            </witness>
          </hasWitnesses>
        </item>
        <item id="admda-l3t5c2">
          <fileName filestem="admda-l3t5c2"/>
          <title>CAPUT II.</title>
          <questionTitle>Quod sensus qui fiunt per media extrinseca, non nutriunt, et qualiter fiunt
            per media extrinseca.</questionTitle>
          <hasWitnesses>
            <witness ref="#B5">
              <folio>414</folio>
              <folio>415</folio>
            </witness>
          </hasWitnesses>
        </item>
        <item id="admda-l3t5c3">
          <fileName filestem="admda-l3t5c3"/>
          <title>CAPUT III.</title>
          <questionTitle>Qualiter sit animalis corpus, utrum simplex aut compositum.</questionTitle>
          <hasWitnesses>
            <witness ref="#B5">
              <folio>415</folio>
              <folio>416</folio>
              <folio>417</folio>
            </witness>
          </hasWitnesses>
        </item>
        <item id="admda-l3t5c4">
          <fileName filestem="admda-l3t5c4"/>
          <title>CAPUT IV.</title>
          <questionTitle>Et est digressio declarans quod sensibile et vegetativum et rationale in
            homine sunt una anima.</questionTitle>
          <hasWitnesses>
            <witness ref="#B5">
              <folio>417</folio>
              <folio>418</folio>
              <folio>419</folio>
              <folio>420</folio>
            </witness>
          </hasWitnesses>
        </item>
      </div>
    </div>
  </div>
</listofFileNames>
