<?xml version="1.0" encoding="UTF-8"?>
<listofFileNames>
  <header>
    <authorName>John Dinsdale</authorName>
    <commentaryName>Quaestiones De anima</commentaryName>
    <commentaryid>dinsdalequaestiones</commentaryid>
    <commentaryslug>49</commentaryslug>
    <authorUri>http://scta.info/resource/JohnDinsdale</authorUri>
    <parentUri>http://scta.info/resource/dinsdalequaestiones</parentUri>
    <parentWorkGroup>http://scta.info/resource/deanima</parentWorkGroup>
  	<textfilesdir>/Users/jcwitt/Projects/scta/scta-texts/dinsdalequaestiones/</textfilesdir>
    <webbase>null</webbase>
    <questionListSource></questionListSource>
    <questionListOriginalEditor>Michael Stenskjær Christensen</questionListOriginalEditor>
    <questionListEncoder>Michael Stenskjær Christensen</questionListEncoder>
    <!-- possible metadata should go here or be added elsewhere
    -->
    <gitRepoBase>https://github.com/mldac/</gitRepoBase>
    <hasWitnesses>
      <witness id="B">
        <slug>bal311</slug>
        <title>Oxford, Balliol College Library 311, ff. 148r-181v</title>
        <initial>B</initial>
      </witness>
      <witness id="O">
        <slug>oriel33</slug>
        <title>Oxford, Oriel College Library 33, ff. 164r-182v</title>
        <initial>O</initial>
      </witness>
    </hasWitnesses>
  </header>
  <!-- Note: Many of the questions have more elaborate titles in the bottom margin of #B than in the main text. How could we handle that? -->
  <div id="body" xml:lang="la">
    <div id="49-librum1">
      <head>
        Liber primus
      </head>
      <item id="49-prooemium">
    	  <fileName filestem="49-prooemium"/>
    	  <title>Prooemium</title>
        <questionTitle/>
    	  <hasWitnesses>
    		  <witness ref="#B">
    			  <folio>148</folio>
    		  </witness>
          <witness ref="#O">
            <folio>164</folio>
          </witness>
    	  </hasWitnesses>
      </item>
      <item id="49-l1q1" type="quaestio">
        <fileName filestem="49-l1q1"/>
        <title>Librum 1, quaestio 1</title>
        <questionTitle>Utrum de anima possit nobis acquiri scientia</questionTitle>
        <hasWitnesses>
          <witness ref="#B">
            <folio>148</folio>
          </witness>
        </hasWitnesses>
      </item>
      <item id="49-l1q2" type="quaestio">
        <fileName filestem="49-l1q2"/>
        <title>Librum 1, quaestio 2</title>
        <questionTitle>Utrum ista scientia sit de anima tamquam de subiecto vel de corpore animato</questionTitle>
        <hasWitnesses>
          <witness ref="#B">
            <folio>148</folio>
            <folio>149</folio>
          </witness>
        </hasWitnesses>
      </item>
      <item id="49-l1q3" type="quaestio">
        <fileName filestem="49-l1q3"/>
        <title>Librum 1, quaestio 3</title>
        <questionTitle>Utrum scientia sit bonum et honorabile.</questionTitle>
        <hasWitnesses>
          <witness ref="#B">
            <folio>149</folio>
          </witness>
        </hasWitnesses>
      </item>
      <item id="49-l1q4" type="quaestio">
        <fileName filestem="49-l1q4"/>
        <title>Librum 1, quaestio 4</title>
        <questionTitle>Utrum scientia de anima sit dignior aliis secundum certitudinem et subiecti nobilitatem</questionTitle>
        <hasWitnesses>
          <witness ref="#B">
            <folio>149</folio>
          </witness>
        </hasWitnesses>
      </item>
      <item id="49-l1q5" type="quaestio">
        <fileName filestem="49-l1q5"/>
        <title>Librum 1, quaestio 5</title>
        <questionTitle>Utrum universale aut naturalis sit aut posterius ut Philosophus dicit</questionTitle>
        <hasWitnesses>
          <witness ref="#B">
            <folio>149</folio>
          </witness>
        </hasWitnesses>
      </item>
      <item id="49-l1q6" type="quaestio">
        <fileName filestem="49-l1q6"/>
        <title>Librum 1, quaestio 6</title>
        <questionTitle>Utrum accidentia magnam partem conferant ad cognoscendum quod quid est.</questionTitle>
        <hasWitnesses>
          <witness ref="#B">
            <folio>150</folio>
          </witness>
        </hasWitnesses>
      </item>
      <item id="49-l1q7" type="quaestio">
        <fileName filestem="49-l1q7"/>
        <title>Librum 1, quaestio 7</title>
        <lemma>Dubitationem autem habet</lemma> <!-- Suggestion for relevant field-->
        <questionTitle>Utrum aliqua sit operatio propria animae.</questionTitle>
        <hasWitnesses>
          <witness ref="#B">
            <folio>150</folio>
          </witness>
        </hasWitnesses>
      </item>
      <item id="49-l1q8" type="quaestio">
        <fileName filestem="49-l1q8"/>
        <title>Librum 1, quaestio 8</title>
        <questionTitle>Utrum physicus in diffiniendo differat ab aliis artificibus.</questionTitle>
        <hasWitnesses>
          <witness ref="#B">
            <folio>150</folio>
            <folio>151</folio>
          </witness>
        </hasWitnesses>
      </item>
    </div>
    <div id="49-librum2">
      <head>
        Liber secundus
      </head>
      <item id="49-l2q1" type="quaestio">
        <fileName filestem="49-l2q1"/>
        <title>Librum 2, quaestio 1</title>
        <lemma>Haec quidem a prioribus tradita et cetera</lemma>
        <questionTitle>Utrum anima sit actus simplex</questionTitle>
        <hasWitnesses>
          <witness ref="#B">
            <folio>151</folio>
          </witness>
        </hasWitnesses>
      </item>
      <item id="40-l2q2" type="quaestio">
        <fileName filestem="40-l2q2"/>
        <title>Librum 2, quaestio 2</title>
        <questionTitle>Utrum omni animae conveniat esse actum corporis</questionTitle>
        <hasWitnesses>
          <witness ref="#B">
            <folio>151</folio>
            <folio>152</folio>
          </witness>
        </hasWitnesses>
      </item>
      <item id="49-l2q3" type="quaestio">
        <fileName filestem="49-l2q3"/>
        <title>Librum 2, quaestio 3</title>
        <questionTitle>Utrum anima sit actus primus et hoc est quaerere utrum corpus cuius actus est anima sit actu ens <unclear>et</unclear> a materia formata.</questionTitle>
        <hasWitnesses>
          <witness ref="#B">
            <folio>152</folio>
            <folio>153</folio>
            <folio>154</folio>
          </witness>
        </hasWitnesses>
      </item>
      <item id="49-l2q4" type="quaestio">
        <fileName filestem="49-l2q4"/>
        <title>Librum 2, quaestio 4</title>
        <questionTitle>Utrum anima naturaliter uniatur tali corpori, scilicet organico.</questionTitle>
        <hasWitnesses>
          <witness ref="#B">
            <folio>154</folio>
          </witness>
        </hasWitnesses>
      </item>
      <item id="49-l2q5" type="quaestio">
        <fileName filestem="49-l2q5"/>
        <title>Librum 2, quaestio 5</title>
        <questionTitle>Utrum ex anima et corpore fiat <unclear>u()e</unclear> unum</questionTitle>
        <hasWitnesses>
          <witness ref="#B">
            <folio>154</folio>
            <folio>155</folio>
          </witness>
        </hasWitnesses>
      </item>
      <item id="49-l2q6" type="quaestio">
        <fileName filestem="49-l2q6"/>
        <title>Librum 2, quaestio 6</title>
        <questionTitle>Utrum in homine vegetativum et sensitivum et intellectivum sint tres animae aut tres potentiae anius animae.</questionTitle>
        <hasWitnesses>
          <witness ref="#B">
            <folio>155</folio>
          </witness>
        </hasWitnesses>
      </item>
      <item id="49-l2q7" type="quaestio">
        <fileName filestem="49-l2q7"/>
        <title>Librum 2, quaestio 7</title>
        <questionTitle>Utrum in parte plantae descisae vel alterius descisi sit anima.</questionTitle>
        <hasWitnesses>
          <witness ref="#B">
            <folio>155</folio>
          </witness>
        </hasWitnesses>
      </item>
      <item id="49-l2q8" type="quaestio">
        <fileName filestem="49-l2q8"/>
        <title>Librum 2, quaestio 8</title>
        <questionTitle>Utrum anima sit potentia.</questionTitle>
        <hasWitnesses>
          <witness ref="#B">
            <folio>155</folio>
            <folio>156</folio>
          </witness>
        </hasWitnesses>
      </item>
      <item id="49-l2q9" type="quaestio">
        <fileName filestem="49-l2q9"/>
        <title>Librum 2, quaestio 9</title>
        <questionTitle>Utrum potentiae distinguntur per actus et obiecta.</questionTitle>
        <hasWitnesses>
          <witness ref="#B">
            <folio>156</folio>
          </witness>
        </hasWitnesses>
      </item>
      <item id="49-l2q10" type="quaestio">
        <fileName filestem="49-l2q10"/>
        <title>Librum 2, quaestio 10</title>
        <questionTitle>Utrum in potentiis animae sit ordo secundum prius et posterius.</questionTitle>
        <hasWitnesses>
          <witness ref="#B">
            <folio>156</folio>
          </witness>
        </hasWitnesses>
      </item>
      <item id="49-l2q11" type="quaestio">
        <fileName filestem="49-l2q11"/>
        <title>Librum 2, quaestio 11</title>
        <questionTitle>Utrum omnis potentiae animae sint in anima tamquam in subiecto.</questionTitle>
        <hasWitnesses>
          <witness ref="#B">
            <folio>156</folio>
          </witness>
        </hasWitnesses>
      </item>
      <item id="49-l2q12" type="quaestio">
        <fileName filestem="49-l2q12"/>
        <title>Librum 2, quaestio 12</title>
        <questionTitle>Utrum quinque sint genera potentiarum animae tantum.</questionTitle>
        <hasWitnesses>
          <witness ref="#B">
            <folio>156</folio>
          </witness>
        </hasWitnesses>
      </item>
      <item id="49-l2q13" type="quaestio">
        <fileName filestem="49-l2q13"/>
        <title>Librum 2, quaestio 13</title>
        <questionTitle>Utrum tres sint potentiae vegetativae, scilicet nutritiva, augmentativa et generativa.</questionTitle>
        <hasWitnesses>
          <witness ref="#B">
            <folio>157</folio>
          </witness>
        </hasWitnesses>
      </item>
      <item id="49-l2q14" type="quaestio">
        <fileName filestem="49-l2q14"/>
        <title>Librum 2, quaestio 14</title>
        <questionTitle>Utrum vegetativa in qualibet operatione habeat alimentum <unclear>pro</unclear> obiecto.</questionTitle>
        <hasWitnesses>
          <witness ref="#B">
            <folio>157</folio>
          </witness>
        </hasWitnesses>
      </item>
      <item id="49-l2q15" type="quaestio">
        <fileName filestem="49-l2q15"/>
        <title>Librum 2, quaestio 15</title>
        <questionTitle>Utrum alimentum convertatur in unam naturam rei.</questionTitle>
        <hasWitnesses>
          <witness ref="#B">
            <folio>157</folio>
          </witness>
        </hasWitnesses>
      </item>
      <item id="49-l2q16" type="quaestio">
        <fileName filestem="49-l2q16"/>
        <title>Librum 2, quaestio 16</title>
        <questionTitle>Utrum semen sit de substantia generantis.</questionTitle>
        <hasWitnesses>
          <witness ref="#B">
            <folio>157</folio>
            <folio>158</folio>
          </witness>
        </hasWitnesses>
      </item>
      <item id="49-l2q17" type="quaestio">
        <fileName filestem="49-l2q17"/>
        <title>Librum 2, quaestio 17</title>
        <questionTitle>Utrum virtus in semine sit productiva sensitivae.</questionTitle>
        <hasWitnesses>
          <witness ref="#B">
            <folio>158</folio>
          </witness>
        </hasWitnesses>
      </item>
      <item id="49-l2q18" type="quaestio">
        <fileName filestem="49-l2q18"/>
        <title>Librum 2, quaestio 18</title>
        <questionTitle>Utrum in semine sit virtus ad producendum intellectivam.</questionTitle>
        <hasWitnesses>
          <witness ref="#B">
            <folio>158</folio>
          </witness>
        </hasWitnesses>
      </item>
      <item id="49-l2q19" type="quaestio">
        <fileName filestem="49-l2q19"/>
        <title>Librum 2, quaestio 19</title>
        <questionTitle>Utrum sensus sit virtus passiva.</questionTitle>
        <hasWitnesses>
          <witness ref="#B">
            <folio>158</folio>
          </witness>
        </hasWitnesses>
      </item>
      <item id="49-l2q20" type="quaestio">
        <fileName filestem="49-l2q20"/>
        <title>Librum 2, quaestio 20</title>
        <questionTitle>Utrum sit ponere sensum agentem.</questionTitle>
        <hasWitnesses>
          <witness ref="#B">
            <folio>158</folio>
            <folio>159</folio>
          </witness>
        </hasWitnesses>
      </item>
      <item id="49-l2q21" type="quaestio">
        <fileName filestem="49-l2q21"/>
        <title>Librum 2, quaestio 21</title>
        <questionTitle>Utrum sensibile proprium sit illud circa quod sensus non decipitur.</questionTitle>
        <hasWitnesses>
          <witness ref="#B">
            <folio>159</folio>
          </witness>
        </hasWitnesses>
      </item>
      <item id="49-l2q22" type="quaestio">
        <fileName filestem="49-l2q22"/>
        <title>Librum 2, quaestio 22</title>
        <questionTitle>Utrum sensibilia communia sunt sensibilia per se.</questionTitle>
        <hasWitnesses>
          <witness ref="#B">
            <folio>159</folio>
          </witness>
        </hasWitnesses>
      </item>
      <item id="49-l2q23" type="quaestio">
        <fileName filestem="49-l2q23"/>
        <title>Librum 2, quaestio 23</title>
        <questionTitle>Utrum Diarii filius et huiusmodi sint sensibilia per accidentiis.</questionTitle>
        <hasWitnesses>
          <witness ref="#B">
            <folio>159</folio>
          </witness>
        </hasWitnesses>
      </item>
      <item id="49-l2q24" type="quaestio">
        <fileName filestem="49-l2q24"/>
        <title>Librum 2, quaestio 24</title>
        <questionTitle>Utrum color sit visibile secundum se et hoc est quaerere utrum lumen requiratur propter neccesitatem coloris vel <unclear>me()ri</unclear></questionTitle>
        <hasWitnesses>
          <witness ref="#B">
            <folio>159</folio>
          </witness>
        </hasWitnesses>
      </item>
      <item id="49-l2q25" type="quaestio">
        <fileName filestem="49-l2q25"/>
        <title>Librum 2, quaestio 25</title>
        <questionTitle>Utrum lux sit de essentia coloris.</questionTitle>
        <hasWitnesses>
          <witness ref="#B">
            <folio>160</folio>
          </witness>
        </hasWitnesses>
      </item>
      <item id="49-l2q26" type="quaestio">
        <fileName filestem="49-l2q26"/>
        <title>Librum 2, quaestio 26</title>
        <questionTitle>Utrum multiplicatio lucis fuerit in instanti vel succesiva.</questionTitle>
        <hasWitnesses>
          <witness ref="#B">
            <folio>160</folio>
          </witness>
        </hasWitnesses>
      </item>
      <item id="49-l2q27" type="quaestio">
        <fileName filestem="49-l2q27"/>
        <title>Librum 2, quaestio 27</title>
        <questionTitle>Utrum posito medio infinito, ipsum lumen possit totum illuminare.</questionTitle>
        <hasWitnesses>
          <witness ref="#B">
            <folio>161</folio>
          </witness>
        </hasWitnesses>
      </item>
      <item id="49-l2q28" type="quaestio">
        <fileName filestem="49-l2q28"/>
        <title>Librum 2, quaestio 28</title>
        <questionTitle>Utrum lumen sit substantia vel accidens.</questionTitle>
        <hasWitnesses>
          <witness ref="#B">
            <folio>161</folio>
          </witness>
        </hasWitnesses>
      </item>
      <item id="49-l2q29" type="quaestio">
        <fileName filestem="49-l2q29"/>
        <title>Librum 2, quaestio 29</title>
        <questionTitle>Utrum alia de nocte tantum videantur ut <unclear>lucentia</unclear> et de die ut colorata.</questionTitle>
        <hasWitnesses>
          <witness ref="#B">
            <folio>161</folio>
          </witness>
        </hasWitnesses>
      </item>
      <item id="49-l2q30" type="quaestio">
        <fileName filestem="49-l2q30"/>
        <title>Librum 2, quaestio 30</title>
        <questionTitle>Utrum visibile supra visum ponitum sentiatur an <unclear>ncio()</unclear> requiratur medium.</questionTitle>
        <hasWitnesses>
          <witness ref="#B">
            <folio>161</folio>
          </witness>
        </hasWitnesses>
      </item>
      <item id="49-l2q31" type="quaestio">
        <fileName filestem="49-l2q30"/>
        <title>Librum 2, quaestio 31</title>
        <questionTitle>Utrum sonus soneretur ex percussione corporum <unclear>et</unclear> ad aera </questionTitle>
        <hasWitnesses>
          <witness ref="#B">
            <folio>161</folio>
            <folio>162</folio>
          </witness>
        </hasWitnesses>
      </item>
      <item id="49-l2q32" type="quaestio">
        <fileName filestem="49-l2q32"/>
        <title>Librum 2, quaestio 32</title>
        <questionTitle>Utrum sonus sit in aere tamquam in subiecto aut in percussitate et percusso.</questionTitle>
        <hasWitnesses>
          <witness ref="#B">
            <folio>162</folio>
          </witness>
        </hasWitnesses>
      </item>
      <item id="49-l2q33" type="quaestio">
        <fileName filestem="49-l2q33"/>
        <title>Librum 2, quaestio 33</title>
        <questionTitle>Utrum sonus multiplicetur ad auditum cum motu aeris.</questionTitle>
        <hasWitnesses>
          <witness ref="#B">
            <folio>162</folio>
          </witness>
        </hasWitnesses>
      </item>
      <item id="49-l2q34" type="quaestio">
        <fileName filestem="49-l2q34"/>
        <title>Librum 2, quaestio 34</title>
        <questionTitle>Utrum sonus sit in medio secundum esse intentionale vel rationale.</questionTitle>
        <hasWitnesses>
          <witness ref="#B">
            <folio>162</folio>
          </witness>
        </hasWitnesses>
      </item>
      <item id="49-l2q35" type="quaestio">
        <fileName filestem="49-l2q35"/>
        <title>Librum 2, quaestio 35</title>
        <questionTitle>Utrum sonus <unclear>directus</unclear> et reflexus ut ecco sit unus.</questionTitle>
        <hasWitnesses>
          <witness ref="#B">
            <folio>162</folio>
            <folio>163</folio>
          </witness>
        </hasWitnesses>
      </item>
      <item id="49-l2q36" type="quaestio">
        <fileName filestem="49-l2q36"/>
        <title>Librum 2, quaestio 36</title>
        <questionTitle>Utrum vox generetur a virtute imaginativa.</questionTitle>
        <hasWitnesses>
          <witness ref="#B">
            <folio>163</folio>
          </witness>
        </hasWitnesses>
      </item>
      <item id="49-l2q37" type="quaestio">
        <fileName filestem="49-l2q37"/>
        <title>Librum 2, quaestio 37</title>
        <questionTitle>Utrum homo habeat peiorem olfactu aliis.</questionTitle>
        <hasWitnesses>
          <witness ref="#B">
            <folio>163</folio>
          </witness>
        </hasWitnesses>
      </item>
      <item id="49-l2q38" type="quaestio">
        <fileName filestem="49-l2q38"/>
        <title>Librum 2, quaestio 38</title>
        <questionTitle>Utrum odor multiplicetur in medio tantum intentionaliter vel cum <unclear>fum()li</unclear>evaporatione.</questionTitle>
        <hasWitnesses>
          <witness ref="#B">
            <folio>163</folio>
          </witness>
        </hasWitnesses>
      </item>
      <item id="49-l2q39" type="quaestio">
        <fileName filestem="49-l2q39"/>
        <title>Librum 2, quaestio 39</title>
        <questionTitle>Utrum gustus sit quidam tactus.</questionTitle>
        <hasWitnesses>
          <witness ref="#B">
            <folio>163</folio>
            <folio>164</folio>
          </witness>
        </hasWitnesses>
      </item>
      <item id="49-l2q40" type="quaestio">
        <fileName filestem="49-l2q40"/>
        <title>Librum 2, quaestio 40</title>
        <questionTitle>Utrum sapor multiplicet se per se.</questionTitle>
        <hasWitnesses>
          <witness ref="#B">
            <folio>164</folio>
          </witness>
        </hasWitnesses>
      </item>
      <item id="49-l2q41" type="quaestio">
        <fileName filestem="49-l2q41"/>
        <title>Librum 2, quaestio 41</title>
        <questionTitle>Utrum sapor multiplicet se intentionaliter vel materialiter.</questionTitle>
        <hasWitnesses>
          <witness ref="#B">
            <folio>164</folio>
          </witness>
        </hasWitnesses>
      </item>
      <item id="49-l2q42" type="quaestio">
        <fileName filestem="49-l2q42"/>
        <title>Librum 2, quaestio 42</title>
        <questionTitle>Utrum tactus sit unus sensus.</questionTitle>
        <hasWitnesses>
          <witness ref="#B">
            <folio>164</folio>
          </witness>
        </hasWitnesses>
      </item>
      <item id="49-l2q43" type="quaestio">
        <fileName filestem="49-l2q43"/>
        <title>Librum 2, quaestio 43</title>
        <questionTitle>Utrum caro sit organum an aliud.</questionTitle>
        <hasWitnesses>
          <witness ref="#B">
            <folio>164</folio>
          </witness>
        </hasWitnesses>
      </item>
      <item id="49-l2q44" type="quaestio">
        <fileName filestem="49-l2q44"/>
        <title>Librum 2, quaestio 44</title>
        <questionTitle>Utrum in tactu requiritur medium extrinsecum.</questionTitle>
        <hasWitnesses>
          <witness ref="#B">
            <folio>164</folio>
            <folio>165</folio>
          </witness>
        </hasWitnesses>
      </item>
      <item id="49-l2q45" type="quaestio">
        <fileName filestem="49-l2q45"/>
        <title>Librum 2, quaestio 45</title>
        <questionTitle>Utrum sensus sit susceptivus specierum sensibilium sine materia.</questionTitle>
        <hasWitnesses>
          <witness ref="#B">
            <folio>165</folio>
          </witness>
        </hasWitnesses>
      </item>
      <item id="49-l2q46" type="quaestio">
        <fileName filestem="49-l2q46"/>
        <title>Librum 2, quaestio 46</title>
        <questionTitle>Utrum excellens sensibile corrumpat sensum.</questionTitle>
        <hasWitnesses>
          <witness ref="#B">
            <folio>165</folio>
          </witness>
        </hasWitnesses>
      </item>
      <item id="49-l2q47" type="quaestio">
        <fileName filestem="49-l2q47"/>
        <title>Librum 2, quaestio 47</title>
        <questionTitle>Utrum sint tantum quinque sensus.</questionTitle>
        <hasWitnesses>
          <witness ref="#B">
            <folio>165</folio>
            <folio>166</folio>
          </witness>
        </hasWitnesses>
      </item>
      <item id="49-l2q48" type="quaestio">
        <fileName filestem="49-l2q48"/>
        <title>Librum 2, quaestio 48</title>
        <questionTitle>Utrum sensus particulariter percipimus nos sentire ut visu videre aut sensu aliquo aut sensu communi.</questionTitle>
        <hasWitnesses>
          <witness ref="#B">
            <folio>166</folio>
          </witness>
        </hasWitnesses>
      </item>
      <item id="49-l2q49" type="quaestio">
        <fileName filestem="49-l2q49"/>
        <title>Librum 2, quaestio 49</title>
        <questionTitle>Utrum oporteat ponere sensum communem propter <unclear>distinctionem</unclear> vel participationem inter sensibilia diversa <unclear>sn(r)e</unclear></questionTitle>
        <hasWitnesses>
          <witness ref="#B">
            <folio>166</folio>
          </witness>
        </hasWitnesses>
      </item>
      <item id="49-l2q50" type="quaestio">
        <fileName filestem="49-l2q50"/>
        <title>Librum 2, quaestio 50</title>
        <questionTitle>Utrum sensus communis sit unicus an plures.</questionTitle>
        <hasWitnesses>
          <witness ref="#B">
            <folio>166</folio>
            <folio>167</folio>
          </witness>
        </hasWitnesses>
      </item>
      <item id="49-l2q51" type="quaestio">
        <fileName filestem="49-l2q51"/>
        <title>Librum 2, quaestio 51</title>
        <questionTitle>Utrum organum sensus communis sit internis iuxta cor vel non.</questionTitle>
        <hasWitnesses>
          <witness ref="#B">
            <folio>167</folio>
          </witness>
        </hasWitnesses>
      </item>
      <item id="49-l2q51" type="quaestio">
        <fileName filestem="49-l2q51"/>
        <title>Librum 2, quaestio 52</title>
        <questionTitle>Utrum sensus communis simul apprehendat sensibilia diversi generis.</questionTitle>
        <hasWitnesses>
          <witness ref="#B">
            <folio>167</folio>
          </witness>
        </hasWitnesses>
      </item>
      <item id="49-l2q52" type="quaestio">
        <fileName filestem="49-l2q52"/>
        <title>Librum 2, quaestio 53</title>
        <questionTitle>Utrum fantasma differat a sensu.</questionTitle>
        <hasWitnesses>
          <witness ref="#B">
            <folio>167</folio>
          </witness>
        </hasWitnesses>
      </item>
      <item id="49-l2q53" type="quaestio">
        <fileName filestem="49-l2q53"/>
        <title>Librum 2, quaestio 54</title>
        <questionTitle>Utrum fantasia sit motus factus a sensu secundum actum.</questionTitle>
        <hasWitnesses>
          <witness ref="#B">
            <folio>167</folio>
            <folio>168</folio>
          </witness>
        </hasWitnesses>
      </item>
      <item id="49-l2q54" type="quaestio">
        <fileName filestem="49-l2q54"/>
        <title>Librum 2, quaestio 55</title>
        <questionTitle>Utrum fantasia insit omni animali.</questionTitle>
        <hasWitnesses>
          <witness ref="#B">
            <folio>168</folio>
          </witness>
        </hasWitnesses>
      </item>
      <item id="49-l2q55" type="quaestio">
        <fileName filestem="49-l2q55"/>
        <title>Librum 2, quaestio 56</title>
        <questionTitle>Utrum opinio pertineat ad sensum vel ad intellectum.</questionTitle>
        <hasWitnesses>
          <witness ref="#B">
            <folio>168</folio>
          </witness>
        </hasWitnesses>
      </item>
      <item id="49-l2q56" type="quaestio">
        <fileName filestem="49-l2q56"/>
        <title>Librum 2, quaestio 57</title>
        <questionTitle>Utrum convenienter distinguantur ista sensus, scilicet sensus communis, imaginativa, aestimativa et memorativa.</questionTitle>
        <hasWitnesses>
          <witness ref="#B">
            <folio>168</folio>
          </witness>
        </hasWitnesses>
      </item>
    </div>
    <div id="49-librum3">
      <head>Liber tertius</head>
      <item id="49-l3q1" type="quaestio">
        <fileName filestem="49-l3q1"/>
        <title>Librum 3, quaestio 1</title>
        <questionTitle>Utrum intellectus sit essentia animae vel potentia.</questionTitle>
        <hasWitnesses>
          <witness ref="#B">
            <folio>168</folio>
            <folio>169</folio>
          </witness>
        </hasWitnesses>
      </item>
      <item id="49-l3q2" type="quaestio">
        <fileName filestem="49-l3q2"/>
        <title>Librum 3, quaestio 2</title>
        <questionTitle>Utrum intellectus sit potentia passiva.</questionTitle>
        <hasWitnesses>
          <witness ref="#B">
            <folio>169</folio>
          </witness>
        </hasWitnesses>
      </item>
      <item id="49-l3q3" type="quaestio">
        <fileName filestem="49-l3q3"/>
        <title>Librum 3, quaestio 3</title>
        <questionTitle>Utrum oporteat intellectu esse immixtum ita quod nullam naturam corpoream habeat ad hoc ut omnia cognoscit.</questionTitle>
        <hasWitnesses>
          <witness ref="#B">
            <folio>169</folio>
          </witness>
        </hasWitnesses>
      </item>
      <item id="49-l3q4" type="quaestio">
        <fileName filestem="49-l3q4"/>
        <title>Librum 3, quaestio 4</title>
        <questionTitle>Utrum oporteat intellectum privari organo ut omnia cognoscit.</questionTitle>
        <hasWitnesses>
          <witness ref="#B">
            <folio>169</folio>
          </witness>
        </hasWitnesses>
      </item>
      <item id="49-l3q5" type="quaestio">
        <fileName filestem="49-l3q5"/>
        <title>Librum 3, quaestio 5</title>
        <questionTitle>Utrum intellectus sit unus numero in omnibus.</questionTitle>
        <hasWitnesses>
          <witness ref="#B">
            <folio>169</folio>
            <folio>170</folio>
          </witness>
        </hasWitnesses>
      </item>
      <item id="49-l3q6" type="quaestio">
        <fileName filestem="49-l3q6"/>
        <title>Librum 3, quaestio 6</title>
        <questionTitle>Utrum intellectus sit incorruptibilis.</questionTitle>
        <hasWitnesses>
          <witness ref="#B">
            <folio>170</folio>
            <folio>171</folio>
          </witness>
        </hasWitnesses>
      </item>
      <item id="49-l3q7" type="quaestio">
        <fileName filestem="49-l3q7"/>
        <title>Librum 3, quaestio 7</title>
        <questionTitle>Utrum anima intellectiva in qualibet parte corporis sit tota.</questionTitle>
        <hasWitnesses>
          <witness ref="#B">
            <folio>171</folio>
          </witness>
        </hasWitnesses>
      </item>
      <item id="49-l3q8" type="quaestio">
        <fileName filestem="49-l3q8"/>
        <title>Librum 3, quaestio 8</title>
        <questionTitle>Utrum intellectus intelligat rem corpoream et sensibilem.</questionTitle>
        <hasWitnesses>
          <witness ref="#B">
            <folio>171</folio>
          </witness>
        </hasWitnesses>
      </item>
      <item id="49-l3q9" type="quaestio">
        <fileName filestem="49-l3q9"/>
        <title>Librum 3, quaestio 9</title>
        <questionTitle>Utrum intellectus intelligat per species a sensibilibus acceptas an per species innatas aliunde adquisitas vel per essentiam vel qualitercumque.</questionTitle>
        <hasWitnesses>
          <witness ref="#B">
            <folio>171</folio>
            <folio>172</folio>
          </witness>
        </hasWitnesses>
      </item>
      <item id="49-l3q10" type="quaestio">
        <fileName filestem="49-l3q10"/>
        <title>Librum 3, quaestio 10</title>
        <questionTitle>Utrum species possint manere in intellectu cum actu non intelligit.</questionTitle>
        <hasWitnesses>
          <witness ref="#B">
            <folio>172</folio>
            <folio>173</folio>
          </witness>
        </hasWitnesses>
      </item>
      <item id="49-l3q11" type="quaestio">
        <fileName filestem="49-l3q11"/>
        <title>Librum 3, quaestio 11</title>
        <questionTitle>Utrum intellectus per species quas praesens se habet, possit intelligere absque hoc quod convertat se ad fantasmata.</questionTitle>
        <hasWitnesses>
          <witness ref="#B">
            <folio>173</folio>
          </witness>
        </hasWitnesses>
      </item>
      <item id="49-l3q12" type="quaestio">
        <fileName filestem="49-l3q12"/>
        <title>Librum 3, quaestio 12</title>
        <questionTitle>Utrum intellectus intelligat res corruptibiles et materiales abstrahendo a fantasmatibus.</questionTitle>
        <hasWitnesses>
          <witness ref="#B">
            <folio>173</folio>
          </witness>
        </hasWitnesses>
      </item>
      <item id="49-l3q13" type="quaestio">
        <fileName filestem="49-l3q13"/>
        <title>Librum 3, quaestio 13</title>
        <questionTitle>Utrum species absracta sit illud quod intelligitur primo et per se aut res cuius est species.</questionTitle>
        <hasWitnesses>
          <witness ref="#B">
            <folio>173</folio>
            <folio>174</folio>
          </witness>
        </hasWitnesses>
      </item>
      <item id="49-l3q14" type="quaestio">
        <fileName filestem="49-l3q14"/>
        <title>Librum 3, quaestio 14</title>
        <questionTitle>Utrum intellectus intelligat singulare per se.</questionTitle>
        <hasWitnesses>
          <witness ref="#B">
            <folio>174</folio>
          </witness>
        </hasWitnesses>
      </item>
      <item id="49-l3q15" type="quaestio">
        <fileName filestem="49-l3q15"/>
        <title>Librum 3, quaestio 15</title>
        <questionTitle>Utrum intellectus intelligat se per suam essentiam an per aliud sicut intelligit alia.</questionTitle>
        <hasWitnesses>
          <witness ref="#B">
            <folio>174</folio>
            <folio>175</folio>
          </witness>
        </hasWitnesses>
      </item>
      <item id="49-l3q16" type="quaestio">
        <fileName filestem="49-l3q16"/>
        <title>Librum 3, quaestio 16</title>
        <questionTitle>Utrum intellectus possibilis sit actu aliquid eorum quae sunt antequam intelligat.</questionTitle>
        <hasWitnesses>
          <witness ref="#B">
            <folio>175</folio>
          </witness>
        </hasWitnesses>
      </item>
      <item id="49-l3q17" type="quaestio">
        <fileName filestem="49-l3q17"/>
        <title>Librum 3, quaestio 17</title>
        <questionTitle>Utrum neccesse sit ponere intellectum agentem.</questionTitle>
        <hasWitnesses>
          <witness ref="#B">
            <folio>175</folio>
          </witness>
        </hasWitnesses>
      </item>
      <item id="49-l3q18" type="quaestio">
        <fileName filestem="49-l3q18"/>
        <title>Librum 3, quaestio 18</title>
        <questionTitle>Utrum intellectus agens sit pars animae nostrae.</questionTitle>
        <hasWitnesses>
          <witness ref="#B">
            <folio>175</folio>
            <folio>176</folio>
          </witness>
        </hasWitnesses>
      </item>
      <item id="49-l3q19" type="quaestio">
        <fileName filestem="49-l3q19"/>
        <title>Librum 3, quaestio 19</title>
        <questionTitle>Utrum intellectus agens abstrahendo intelligat.</questionTitle>
        <hasWitnesses>
          <witness ref="#B">
            <folio>176</folio>
          </witness>
        </hasWitnesses>
      </item>
      <item id="49-l3q20" type="quaestio">
        <fileName filestem="49-l3q20"/>
        <title>Librum 3, quaestio 20</title>
        <questionTitle>Utrum omnia a nobis intellecta fiant intellecta per intellectum agentem.</questionTitle>
        <hasWitnesses>
          <witness ref="#B">
            <folio>176</folio>
            <folio>177</folio>
          </witness>
        </hasWitnesses>
      </item>
      <item id="49-l3q21" type="quaestio">
        <fileName filestem="49-l3q21"/>
        <title>Librum 3, quaestio 21</title>
        <questionTitle>Utrum genera quae est huius intellectus obiectum faciat ex re speciem per quam cognoscat sicut et a materia.</questionTitle>
        <hasWitnesses>
          <witness ref="#B">
            <folio>176</folio>
            <folio>177</folio>
          </witness>
        </hasWitnesses>
      </item>
      <item id="49-l3q22" type="quaestio">
        <fileName filestem="49-l3q22"/>
        <title>Librum 3, quaestio 22</title>
        <questionTitle>Utrum intellectus noster intelligat componendo et dividendo.</questionTitle>
        <hasWitnesses>
          <witness ref="#B">
            <folio>177</folio>
          </witness>
        </hasWitnesses>
      </item>
      <item id="49-l3q23" type="quaestio">
        <fileName filestem="49-l3q23"/>
        <title>Librum 3, quaestio 23</title>
        <questionTitle>Utrum intellectus per prius intelligat divisibile quam indivisibile et videtur quod per prius intelligat indivisibile.</questionTitle>
        <hasWitnesses>
          <witness ref="#B">
            <folio>177</folio>
          </witness>
        </hasWitnesses>
      </item>
      <item id="49-l3q24" type="quaestio">
        <fileName filestem="49-l3q24"/>
        <title>Librum 3, quaestio 24</title>
        <questionTitle>Utrum intellectus possit esse falsus.</questionTitle>
        <hasWitnesses>
          <witness ref="#B">
            <folio>177</folio>
          </witness>
        </hasWitnesses>
      </item>
      <item id="49-l3q25" type="quaestio">
        <fileName filestem="49-l3q25"/>
        <title>Librum 3, quaestio 25</title>
        <questionTitle>Utrum verum et falsum primo et principaliter sit in intellectu componente et dividente.</questionTitle>
        <hasWitnesses>
          <witness ref="#B">
            <folio>177</folio>
            <folio>178</folio>
          </witness>
        </hasWitnesses>
      </item>
      <item id="49-l3q26" type="quaestio">
        <fileName filestem="49-l3q26"/>
        <title>Librum 3, quaestio 26</title>
        <questionTitle>Utrum intellectus practicus et speculativus sint diversae potentiae.</questionTitle>
        <hasWitnesses>
          <witness ref="#B">
            <folio>178</folio>
          </witness>
        </hasWitnesses>
      </item>
      <item id="49-l3q27" type="quaestio">
        <fileName filestem="49-l3q27"/>
        <title>Librum 3, quaestio 27</title>
        <questionTitle>Utrum sit ponere plures potentias in parte intellectiva quam possibilem et agentem.</questionTitle>
        <hasWitnesses>
          <witness ref="#B">
            <folio>178</folio>
          </witness>
        </hasWitnesses>
      </item>
      <item id="49-l3q28" type="quaestio">
        <fileName filestem="49-l3q28"/>
        <title>Librum 3, quaestio 28</title>
        <questionTitle>Utrum intellectus noster magnitudine coniunctus possit cognoscere vel intelligere.</questionTitle>
        <hasWitnesses>
          <witness ref="#B">
            <folio>178</folio>
            <folio>179</folio>
          </witness>
        </hasWitnesses>
      </item>
      <item id="49-l3q29" type="quaestio">
        <fileName filestem="49-l3q29"/>
        <title>Librum 3, quaestio 29</title>
        <questionTitle>Utrum appetivum sit distinctum ab aliis potentiis animae.</questionTitle>
        <hasWitnesses>
          <witness ref="#B">
            <folio>179</folio>
          </witness>
        </hasWitnesses>
      </item>
      <item id="49-l3q30" type="quaestio">
        <fileName filestem="49-l3q30"/>
        <title>Librum 3, quaestio 30</title>
        <questionTitle>Utrum appetitus dividatur in rationalem et sensitivum.</questionTitle>
        <hasWitnesses>
          <witness ref="#B">
            <folio>179</folio>
          </witness>
        </hasWitnesses>
      </item>
      <item id="49-l3q31" type="quaestio">
        <fileName filestem="49-l3q31"/>
        <title>Librum 3, quaestio 31</title>
        <questionTitle>Utrum appetitus sensitivus dividatur in irascibilem et concupibilem.</questionTitle>
        <hasWitnesses>
          <witness ref="#B">
            <folio>179</folio>
          </witness>
        </hasWitnesses>
      </item>
      <item id="49-l3q32" type="quaestio">
        <fileName filestem="49-l3q32"/>
        <title>Librum 3, quaestio 32</title>
        <questionTitle>Utrum appetitus rationalis dividitur in irascibilem et concupibilem.</questionTitle>
        <hasWitnesses>
          <witness ref="#B">
            <folio>179</folio>
            <folio>180</folio>
          </witness>
        </hasWitnesses>
      </item>
      <item id="49-l3q33" type="quaestio">
        <fileName filestem="49-l3q33"/>
        <title>Librum 3, quaestio 33</title>
        <questionTitle>Utrum voluntas quae est appetitus rationalis sit nobilior potentia quam intellectus</questionTitle>
        <hasWitnesses>
          <witness ref="#B">
            <folio>180</folio>
          </witness>
        </hasWitnesses>
      </item>
      <item id="49-l3q34" type="quaestio">
        <fileName filestem="49-l3q34"/>
        <title>Librum 3, quaestio 34</title>
        <questionTitle>Utrum appetitus rationalis quae est voluntas moveat intellectum.</questionTitle>
        <hasWitnesses>
          <witness ref="#B">
            <folio>180</folio>
          </witness>
        </hasWitnesses>
      </item>
      <item id="49-l3q35" type="quaestio">
        <fileName filestem="49-l3q35"/>
        <title>Librum 3, quaestio 35</title>
        <questionTitle>Utrum appetitus sensitivus aboediat intellectu et rationi.</questionTitle>
        <hasWitnesses>
          <witness ref="#B">
            <folio>180</folio>
            <folio>181</folio>
          </witness>
        </hasWitnesses>
      </item>
      <item id="49-l3q36" type="quaestio">
        <fileName filestem="49-l3q36"/>
        <title>Librum 3, quaestio 36</title>
        <questionTitle>Utrum intellectus et appetitus et appetibile moveant.</questionTitle>
        <hasWitnesses>
          <witness ref="#B">
            <folio>181</folio>
          </witness>
        </hasWitnesses>
      </item>
      <item id="49-l3q37" type="quaestio">
        <fileName filestem="49-l3q37"/>
        <title>Librum 3, quaestio 37</title>
        <questionTitle>Utrum potentia motiva ab aliis sit distincta.</questionTitle>
        <hasWitnesses>
          <witness ref="#B">
            <folio>181</folio>
          </witness>
        </hasWitnesses>
      </item>
      <item id="49-l3q38" type="quaest">
        <fileName filestem="49-l3q38"/>
        <title>Librum 3, quaestio 38</title>
        <questionTitle>Utrum animalis moti ex se neccesse est a materia partem quiescere et immobilem esse.</questionTitle>
        <hasWitnesses>
          <witness ref="id">
            <folio>num</folio>
          </witness>
        </hasWitnesses>
      </item>
    </div>
	</div>
</listofFileNames>
