<?xml version="1.0" encoding="UTF-8"?><?xml-model href="https://raw.githubusercontent.com/scta/edf-schema/master/src/projectfile.rng" type="application/xml" schematypens="http://relaxng.org/ns/structure/1.0"?><listofFileNames>
  <header>
    <authorName>Innocent III</authorName>
    <commentaryName>Fourth Lateran Council</commentaryName>
    <commentaryid>nhyjhg</commentaryid>
    <commentaryslug>nhyjhg</commentaryslug>
    <alias>fourthlaterancouncil</alias>
    <authorUri>http://scta.info/resource/PopeInnocentIII</authorUri>
    <parentUri>http://scta.info/resource/nhyjhg</parentUri>
    <parentWorkGroup>http://scta.info/resource/canonlaw</parentWorkGroup>
    <textfilesdir>/Users/jcwitt/Projects/scta/scta-texts/nhyjhg/</textfilesdir>
    <questionListSource/>
    <questionListOriginalEditor/>
    <questionListEncoder>Jeffrey C. Witt</questionListEncoder>
    <gitRepoBase type="toplevel">https://github.com/scta-texts/</gitRepoBase>
    <hasWitnesses>
    </hasWitnesses>
  </header>
  <div id="body">
    <item id="nhyjhg-d1e51" alias="nhyjhg-c1">
      <fileName filestem="nhyjhg-d1e51"/>
      <title>Canon 1</title>
    </item>
    <item id="nhyjhg-d1e59" alias="nhyjhg-c2">
      <fileName filestem="nhyjhg-d1e59"/>
      <title>Canon 2</title>
    </item>
    <item id="nhyjhg-d1e67" alias="nhyjhg-c3">
      <fileName filestem="nhyjhg-d1e67"/>
      <title>Canon 3</title>
    </item>
    <item id="nhyjhg-d1e75" alias="nhyjhg-c4">
      <fileName filestem="nhyjhg-d1e75"/>
      <title>Canon 4</title>
    </item>
    <item id="nhyjhg-d1e83" alias="nhyjhg-c5">
      <fileName filestem="nhyjhg-d1e83"/>
      <title>Canon 5</title>
    </item>
    <item id="nhyjhg-d1e92" alias="nhyjhg-c6">
      <fileName filestem="nhyjhg-d1e92"/>
      <title>Canon 6</title>
    </item>
    <item id="nhyjhg-d1e100" alias="nhyjhg-c7">
      <fileName filestem="nhyjhg-d1e100"/>
      <title>Canon 7</title>
    </item>
    <item id="nhyjhg-d1e108" alias="nhyjhg-c8">
      <fileName filestem="nhyjhg-d1e108"/>
      <title>Canon 8</title>
    </item>
    <item id="nhyjhg-d1e116" alias="nhyjhg-c9">
      <fileName filestem="nhyjhg-d1e116"/>
      <title>Canon 9</title>
    </item>
    <item id="nhyjhg-d1e124" alias="nhyjhg-c10">
      <fileName filestem="nhyjhg-d1e124"/>
      <title>Canon 10</title>
    </item>
    <item id="nhyjhg-d1e132" alias="nhyjhg-c11">
      <fileName filestem="nhyjhg-d1e132"/>
      <title>Canon 11</title>
    </item>
    <item id="nhyjhg-d1e141" alias="nhyjhg-c12">
      <fileName filestem="nhyjhg-d1e141"/>
      <title>Canon 12</title>
    </item>
    <item id="nhyjhg-d1e149" alias="nhyjhg-c13">
      <fileName filestem="nhyjhg-d1e149"/>
      <title>Canon 13</title>
    </item>
    <item id="nhyjhg-d1e157" alias="nhyjhg-c14">
      <fileName filestem="nhyjhg-d1e157"/>
      <title>Canon 14</title>
    </item>
    <item id="nhyjhg-d1e165" alias="nhyjhg-c15">
      <fileName filestem="nhyjhg-d1e165"/>
      <title>Canon 15</title>
    </item>
    <item id="nhyjhg-d1e173" alias="nhyjhg-c16">
      <fileName filestem="nhyjhg-d1e173"/>
      <title>Canon 16</title>
    </item>
    <item id="nhyjhg-d1e181" alias="nhyjhg-c17">
      <fileName filestem="nhyjhg-d1e181"/>
      <title>Canon 17</title>
    </item>
    <item id="nhyjhg-d1e190" alias="nhyjhg-c18">
      <fileName filestem="nhyjhg-d1e190"/>
      <title>Canon 18</title>
    </item>
    <item id="nhyjhg-d1e198" alias="nhyjhg-c19">
      <fileName filestem="nhyjhg-d1e198"/>
      <title>Canon 19</title>
    </item>
    <item id="nhyjhg-d1e206" alias="nhyjhg-c20">
      <fileName filestem="nhyjhg-d1e206"/>
      <title>Canon 20</title>
    </item>
    <item id="nhyjhg-d1e214" alias="nhyjhg-c21">
      <fileName filestem="nhyjhg-d1e214"/>
      <title>Canon 21</title>
    </item>
    <item id="nhyjhg-d1e222" alias="nhyjhg-c22">
      <fileName filestem="nhyjhg-d1e222"/>
      <title>Canon 22</title>
    </item>
    <item id="nhyjhg-d1e230" alias="nhyjhg-c23">
      <fileName filestem="nhyjhg-d1e230"/>
      <title>Canon 23</title>
    </item>
    <item id="nhyjhg-d1e239" alias="nhyjhg-c24">
      <fileName filestem="nhyjhg-d1e239"/>
      <title>Canon 24</title>
    </item>
    <item id="nhyjhg-d1e247" alias="nhyjhg-c25">
      <fileName filestem="nhyjhg-d1e247"/>
      <title>Canon 25</title>
    </item>
    <item id="nhyjhg-d1e255" alias="nhyjhg-c26">
      <fileName filestem="nhyjhg-d1e255"/>
      <title>Canon 26</title>
    </item>
    <item id="nhyjhg-d1e263" alias="nhyjhg-c27">
      <fileName filestem="nhyjhg-d1e263"/>
      <title>Canon 27</title>
    </item>
    <item id="nhyjhg-d1e271" alias="nhyjhg-c28">
      <fileName filestem="nhyjhg-d1e271"/>
      <title>Canon 28</title>
    </item>
    <item id="nhyjhg-d1e279" alias="nhyjhg-c29">
      <fileName filestem="nhyjhg-d1e279"/>
      <title>Canon 29</title>
    </item>
    <item id="nhyjhg-d1e288" alias="nhyjhg-c30">
      <fileName filestem="nhyjhg-d1e288"/>
      <title>Canon 30</title>
    </item>
    <item id="nhyjhg-d1e296" alias="nhyjhg-c31">
      <fileName filestem="nhyjhg-d1e296"/>
      <title>Canon 31</title>
    </item>
    <item id="nhyjhg-d1e304" alias="nhyjhg-c32">
      <fileName filestem="nhyjhg-d1e304"/>
      <title>Canon 32</title>
    </item>
    <item id="nhyjhg-d1e312" alias="nhyjhg-c33">
      <fileName filestem="nhyjhg-d1e312"/>
      <title>Canon 33</title>
    </item>
    <item id="nhyjhg-d1e320" alias="nhyjhg-c34">
      <fileName filestem="nhyjhg-d1e320"/>
      <title>Canon 34</title>
    </item>
    <item id="nhyjhg-d1e328" alias="nhyjhg-c35">
      <fileName filestem="nhyjhg-d1e328"/>
      <title>Canon 35</title>
    </item>
    <item id="nhyjhg-d1e337" alias="nhyjhg-c36">
      <fileName filestem="nhyjhg-d1e337"/>
      <title>Canon 36</title>
    </item>
    <item id="nhyjhg-d1e345" alias="nhyjhg-c37">
      <fileName filestem="nhyjhg-d1e345"/>
      <title>Canon 37</title>
    </item>
    <item id="nhyjhg-d1e353" alias="nhyjhg-c38">
      <fileName filestem="nhyjhg-d1e353"/>
      <title>Canon 38</title>
    </item>
    <item id="nhyjhg-d1e361" alias="nhyjhg-c39">
      <fileName filestem="nhyjhg-d1e361"/>
      <title>Canon 39</title>
    </item>
    <item id="nhyjhg-d1e369" alias="nhyjhg-c40">
      <fileName filestem="nhyjhg-d1e369"/>
      <title>Canon 40</title>
    </item>
    <item id="nhyjhg-d1e377" alias="nhyjhg-c41">
      <fileName filestem="nhyjhg-d1e377"/>
      <title>Canon 41</title>
    </item>
    <item id="nhyjhg-d1e386" alias="nhyjhg-c42">
      <fileName filestem="nhyjhg-d1e386"/>
      <title>Canon 42</title>
    </item>
    <item id="nhyjhg-d1e394" alias="nhyjhg-c43">
      <fileName filestem="nhyjhg-d1e394"/>
      <title>Canon 43</title>
    </item>
    <item id="nhyjhg-d1e402" alias="nhyjhg-c44">
      <fileName filestem="nhyjhg-d1e402"/>
      <title>Canon 44</title>
    </item>
    <item id="nhyjhg-d1e410" alias="nhyjhg-c45">
      <fileName filestem="nhyjhg-d1e410"/>
      <title>Canon 45</title>
    </item>
    <item id="nhyjhg-d1e418" alias="nhyjhg-c46">
      <fileName filestem="nhyjhg-d1e418"/>
      <title>Canon 46</title>
    </item>
    <item id="nhyjhg-d1e426" alias="nhyjhg-c47">
      <fileName filestem="nhyjhg-d1e426"/>
      <title>Canon 47</title>
    </item>
    <item id="nhyjhg-d1e435" alias="nhyjhg-c48">
      <fileName filestem="nhyjhg-d1e435"/>
      <title>Canon 48</title>
    </item>
    <item id="nhyjhg-d1e443" alias="nhyjhg-c49">
      <fileName filestem="nhyjhg-d1e443"/>
      <title>Canon 49</title>
    </item>
    <item id="nhyjhg-d1e451" alias="nhyjhg-c50">
      <fileName filestem="nhyjhg-d1e451"/>
      <title>Canon 50</title>
    </item>
    <item id="nhyjhg-d1e459" alias="nhyjhg-c51">
      <fileName filestem="nhyjhg-d1e459"/>
      <title>Canon 51</title>
    </item>
    <item id="nhyjhg-d1e467" alias="nhyjhg-c52">
      <fileName filestem="nhyjhg-d1e467"/>
      <title>Canon 52</title>
    </item>
    <item id="nhyjhg-d1e475" alias="nhyjhg-c53">
      <fileName filestem="nhyjhg-d1e475"/>
      <title>Canon 53</title>
    </item>
    <item id="nhyjhg-d1e484" alias="nhyjhg-c54">
      <fileName filestem="nhyjhg-d1e484"/>
      <title>Canon 54</title>
    </item>
    <item id="nhyjhg-d1e492" alias="nhyjhg-c55">
      <fileName filestem="nhyjhg-d1e492"/>
      <title>Canon 55</title>
    </item>
    <item id="nhyjhg-d1e500" alias="nhyjhg-c56">
      <fileName filestem="nhyjhg-d1e500"/>
      <title>Canon 56</title>
    </item>
    <item id="nhyjhg-d1e508" alias="nhyjhg-c57">
      <fileName filestem="nhyjhg-d1e508"/>
      <title>Canon 57</title>
    </item>
    <item id="nhyjhg-d1e516" alias="nhyjhg-c58">
      <fileName filestem="nhyjhg-d1e516"/>
      <title>Canon 58</title>
    </item>
    <item id="nhyjhg-d1e524" alias="nhyjhg-c59">
      <fileName filestem="nhyjhg-d1e524"/>
      <title>Canon 59</title>
    </item>
    <item id="nhyjhg-d1e533" alias="nhyjhg-c60">
      <fileName filestem="nhyjhg-d1e533"/>
      <title>Canon 60</title>
    </item>
    <item id="nhyjhg-d1e541" alias="nhyjhg-c61">
      <fileName filestem="nhyjhg-d1e541"/>
      <title>Canon 61</title>
    </item>
    <item id="nhyjhg-d1e549" alias="nhyjhg-c62">
      <fileName filestem="nhyjhg-d1e549"/>
      <title>Canon 62</title>
    </item>
    <item id="nhyjhg-d1e557" alias="nhyjhg-c63">
      <fileName filestem="nhyjhg-d1e557"/>
      <title>Canon 63</title>
    </item>
    <item id="nhyjhg-d1e565" alias="nhyjhg-c64">
      <fileName filestem="nhyjhg-d1e565"/>
      <title>Canon 64</title>
    </item>
    <item id="nhyjhg-d1e573" alias="nhyjhg-c65">
      <fileName filestem="nhyjhg-d1e573"/>
      <title>Canon 65</title>
    </item>
    <item id="nhyjhg-d1e582" alias="nhyjhg-c66">
      <fileName filestem="nhyjhg-d1e582"/>
      <title>Canon 66</title>
    </item>
    <item id="nhyjhg-d1e590" alias="nhyjhg-c67">
      <fileName filestem="nhyjhg-d1e590"/>
      <title>Canon 67</title>
    </item>
    <item id="nhyjhg-d1e598" alias="nhyjhg-c68">
      <fileName filestem="nhyjhg-d1e598"/>
      <title>Canon 68</title>
    </item>
    <item id="nhyjhg-d1e606" alias="nhyjhg-c69">
      <fileName filestem="nhyjhg-d1e606"/>
      <title>Canon 69</title>
    </item>
    <item id="nhyjhg-d1e614" alias="nhyjhg-c70">
      <fileName filestem="nhyjhg-d1e614"/>
      <title>Canon 70</title>
    </item>
  </div>
</listofFileNames>